package org.bouncycastle2.crypto.digests;

public class RIPEMD160Digest extends GeneralDigest
{
  private static final int DIGEST_LENGTH = 20;
  private int H0;
  private int H1;
  private int H2;
  private int H3;
  private int H4;
  private int[] X = new int[16];
  private int xOff;

  public RIPEMD160Digest()
  {
    reset();
  }

  public RIPEMD160Digest(RIPEMD160Digest paramRIPEMD160Digest)
  {
    super(paramRIPEMD160Digest);
    this.H0 = paramRIPEMD160Digest.H0;
    this.H1 = paramRIPEMD160Digest.H1;
    this.H2 = paramRIPEMD160Digest.H2;
    this.H3 = paramRIPEMD160Digest.H3;
    this.H4 = paramRIPEMD160Digest.H4;
    System.arraycopy(paramRIPEMD160Digest.X, 0, this.X, 0, paramRIPEMD160Digest.X.length);
    this.xOff = paramRIPEMD160Digest.xOff;
  }

  private int RL(int paramInt1, int paramInt2)
  {
    return paramInt1 << paramInt2 | paramInt1 >>> 32 - paramInt2;
  }

  private int f1(int paramInt1, int paramInt2, int paramInt3)
  {
    return paramInt3 ^ (paramInt1 ^ paramInt2);
  }

  private int f2(int paramInt1, int paramInt2, int paramInt3)
  {
    return paramInt1 & paramInt2 | paramInt3 & (paramInt1 ^ 0xFFFFFFFF);
  }

  private int f3(int paramInt1, int paramInt2, int paramInt3)
  {
    return paramInt3 ^ (paramInt1 | paramInt2 ^ 0xFFFFFFFF);
  }

  private int f4(int paramInt1, int paramInt2, int paramInt3)
  {
    return paramInt1 & paramInt3 | paramInt2 & (paramInt3 ^ 0xFFFFFFFF);
  }

  private int f5(int paramInt1, int paramInt2, int paramInt3)
  {
    return paramInt1 ^ (paramInt2 | paramInt3 ^ 0xFFFFFFFF);
  }

  private void unpackWord(int paramInt1, byte[] paramArrayOfByte, int paramInt2)
  {
    paramArrayOfByte[paramInt2] = ((byte)paramInt1);
    paramArrayOfByte[(paramInt2 + 1)] = ((byte)(paramInt1 >>> 8));
    paramArrayOfByte[(paramInt2 + 2)] = ((byte)(paramInt1 >>> 16));
    paramArrayOfByte[(paramInt2 + 3)] = ((byte)(paramInt1 >>> 24));
  }

  public int doFinal(byte[] paramArrayOfByte, int paramInt)
  {
    finish();
    unpackWord(this.H0, paramArrayOfByte, paramInt);
    unpackWord(this.H1, paramArrayOfByte, paramInt + 4);
    unpackWord(this.H2, paramArrayOfByte, paramInt + 8);
    unpackWord(this.H3, paramArrayOfByte, paramInt + 12);
    unpackWord(this.H4, paramArrayOfByte, paramInt + 16);
    reset();
    return 20;
  }

  public String getAlgorithmName()
  {
    return "RIPEMD160";
  }

  public int getDigestSize()
  {
    return 20;
  }

  // ERROR //
  protected void processBlock()
  {
    // Byte code:
    //   0: aload_0
    //   1: getfield 30	org/bouncycastle2/crypto/digests/RIPEMD160Digest:H0	I
    //   4: istore_1
    //   5: aload_0
    //   6: getfield 32	org/bouncycastle2/crypto/digests/RIPEMD160Digest:H1	I
    //   9: istore_2
    //   10: aload_0
    //   11: getfield 34	org/bouncycastle2/crypto/digests/RIPEMD160Digest:H2	I
    //   14: istore_3
    //   15: aload_0
    //   16: getfield 36	org/bouncycastle2/crypto/digests/RIPEMD160Digest:H3	I
    //   19: istore 4
    //   21: aload_0
    //   22: getfield 38	org/bouncycastle2/crypto/digests/RIPEMD160Digest:H4	I
    //   25: istore 5
    //   27: iload 5
    //   29: aload_0
    //   30: iload_1
    //   31: aload_0
    //   32: iload_2
    //   33: iload_3
    //   34: iload 4
    //   36: invokespecial 72	org/bouncycastle2/crypto/digests/RIPEMD160Digest:f1	(III)I
    //   39: iadd
    //   40: aload_0
    //   41: getfield 21	org/bouncycastle2/crypto/digests/RIPEMD160Digest:X	[I
    //   44: iconst_0
    //   45: iaload
    //   46: iadd
    //   47: bipush 11
    //   49: invokespecial 74	org/bouncycastle2/crypto/digests/RIPEMD160Digest:RL	(II)I
    //   52: iadd
    //   53: istore 6
    //   55: aload_0
    //   56: iload_3
    //   57: bipush 10
    //   59: invokespecial 74	org/bouncycastle2/crypto/digests/RIPEMD160Digest:RL	(II)I
    //   62: istore 7
    //   64: iload 4
    //   66: aload_0
    //   67: iload 5
    //   69: aload_0
    //   70: iload 6
    //   72: iload_2
    //   73: iload 7
    //   75: invokespecial 72	org/bouncycastle2/crypto/digests/RIPEMD160Digest:f1	(III)I
    //   78: iadd
    //   79: aload_0
    //   80: getfield 21	org/bouncycastle2/crypto/digests/RIPEMD160Digest:X	[I
    //   83: iconst_1
    //   84: iaload
    //   85: iadd
    //   86: bipush 14
    //   88: invokespecial 74	org/bouncycastle2/crypto/digests/RIPEMD160Digest:RL	(II)I
    //   91: iadd
    //   92: istore 8
    //   94: aload_0
    //   95: iload_2
    //   96: bipush 10
    //   98: invokespecial 74	org/bouncycastle2/crypto/digests/RIPEMD160Digest:RL	(II)I
    //   101: istore 9
    //   103: iload 7
    //   105: aload_0
    //   106: iload 4
    //   108: aload_0
    //   109: iload 8
    //   111: iload 6
    //   113: iload 9
    //   115: invokespecial 72	org/bouncycastle2/crypto/digests/RIPEMD160Digest:f1	(III)I
    //   118: iadd
    //   119: aload_0
    //   120: getfield 21	org/bouncycastle2/crypto/digests/RIPEMD160Digest:X	[I
    //   123: iconst_2
    //   124: iaload
    //   125: iadd
    //   126: bipush 15
    //   128: invokespecial 74	org/bouncycastle2/crypto/digests/RIPEMD160Digest:RL	(II)I
    //   131: iadd
    //   132: istore 10
    //   134: aload_0
    //   135: iload 6
    //   137: bipush 10
    //   139: invokespecial 74	org/bouncycastle2/crypto/digests/RIPEMD160Digest:RL	(II)I
    //   142: istore 11
    //   144: iload 9
    //   146: aload_0
    //   147: iload 7
    //   149: aload_0
    //   150: iload 10
    //   152: iload 8
    //   154: iload 11
    //   156: invokespecial 72	org/bouncycastle2/crypto/digests/RIPEMD160Digest:f1	(III)I
    //   159: iadd
    //   160: aload_0
    //   161: getfield 21	org/bouncycastle2/crypto/digests/RIPEMD160Digest:X	[I
    //   164: iconst_3
    //   165: iaload
    //   166: iadd
    //   167: bipush 12
    //   169: invokespecial 74	org/bouncycastle2/crypto/digests/RIPEMD160Digest:RL	(II)I
    //   172: iadd
    //   173: istore 12
    //   175: aload_0
    //   176: iload 8
    //   178: bipush 10
    //   180: invokespecial 74	org/bouncycastle2/crypto/digests/RIPEMD160Digest:RL	(II)I
    //   183: istore 13
    //   185: iload 11
    //   187: aload_0
    //   188: iload 9
    //   190: aload_0
    //   191: iload 12
    //   193: iload 10
    //   195: iload 13
    //   197: invokespecial 72	org/bouncycastle2/crypto/digests/RIPEMD160Digest:f1	(III)I
    //   200: iadd
    //   201: aload_0
    //   202: getfield 21	org/bouncycastle2/crypto/digests/RIPEMD160Digest:X	[I
    //   205: iconst_4
    //   206: iaload
    //   207: iadd
    //   208: iconst_5
    //   209: invokespecial 74	org/bouncycastle2/crypto/digests/RIPEMD160Digest:RL	(II)I
    //   212: iadd
    //   213: istore 14
    //   215: aload_0
    //   216: iload 10
    //   218: bipush 10
    //   220: invokespecial 74	org/bouncycastle2/crypto/digests/RIPEMD160Digest:RL	(II)I
    //   223: istore 15
    //   225: iload 13
    //   227: aload_0
    //   228: iload 11
    //   230: aload_0
    //   231: iload 14
    //   233: iload 12
    //   235: iload 15
    //   237: invokespecial 72	org/bouncycastle2/crypto/digests/RIPEMD160Digest:f1	(III)I
    //   240: iadd
    //   241: aload_0
    //   242: getfield 21	org/bouncycastle2/crypto/digests/RIPEMD160Digest:X	[I
    //   245: iconst_5
    //   246: iaload
    //   247: iadd
    //   248: bipush 8
    //   250: invokespecial 74	org/bouncycastle2/crypto/digests/RIPEMD160Digest:RL	(II)I
    //   253: iadd
    //   254: istore 16
    //   256: aload_0
    //   257: iload 12
    //   259: bipush 10
    //   261: invokespecial 74	org/bouncycastle2/crypto/digests/RIPEMD160Digest:RL	(II)I
    //   264: istore 17
    //   266: iload 15
    //   268: aload_0
    //   269: iload 13
    //   271: aload_0
    //   272: iload 16
    //   274: iload 14
    //   276: iload 17
    //   278: invokespecial 72	org/bouncycastle2/crypto/digests/RIPEMD160Digest:f1	(III)I
    //   281: iadd
    //   282: aload_0
    //   283: getfield 21	org/bouncycastle2/crypto/digests/RIPEMD160Digest:X	[I
    //   286: bipush 6
    //   288: iaload
    //   289: iadd
    //   290: bipush 7
    //   292: invokespecial 74	org/bouncycastle2/crypto/digests/RIPEMD160Digest:RL	(II)I
    //   295: iadd
    //   296: istore 18
    //   298: aload_0
    //   299: iload 14
    //   301: bipush 10
    //   303: invokespecial 74	org/bouncycastle2/crypto/digests/RIPEMD160Digest:RL	(II)I
    //   306: istore 19
    //   308: iload 17
    //   310: aload_0
    //   311: iload 15
    //   313: aload_0
    //   314: iload 18
    //   316: iload 16
    //   318: iload 19
    //   320: invokespecial 72	org/bouncycastle2/crypto/digests/RIPEMD160Digest:f1	(III)I
    //   323: iadd
    //   324: aload_0
    //   325: getfield 21	org/bouncycastle2/crypto/digests/RIPEMD160Digest:X	[I
    //   328: bipush 7
    //   330: iaload
    //   331: iadd
    //   332: bipush 9
    //   334: invokespecial 74	org/bouncycastle2/crypto/digests/RIPEMD160Digest:RL	(II)I
    //   337: iadd
    //   338: istore 20
    //   340: aload_0
    //   341: iload 16
    //   343: bipush 10
    //   345: invokespecial 74	org/bouncycastle2/crypto/digests/RIPEMD160Digest:RL	(II)I
    //   348: istore 21
    //   350: iload 19
    //   352: aload_0
    //   353: iload 17
    //   355: aload_0
    //   356: iload 20
    //   358: iload 18
    //   360: iload 21
    //   362: invokespecial 72	org/bouncycastle2/crypto/digests/RIPEMD160Digest:f1	(III)I
    //   365: iadd
    //   366: aload_0
    //   367: getfield 21	org/bouncycastle2/crypto/digests/RIPEMD160Digest:X	[I
    //   370: bipush 8
    //   372: iaload
    //   373: iadd
    //   374: bipush 11
    //   376: invokespecial 74	org/bouncycastle2/crypto/digests/RIPEMD160Digest:RL	(II)I
    //   379: iadd
    //   380: istore 22
    //   382: aload_0
    //   383: iload 18
    //   385: bipush 10
    //   387: invokespecial 74	org/bouncycastle2/crypto/digests/RIPEMD160Digest:RL	(II)I
    //   390: istore 23
    //   392: iload 21
    //   394: aload_0
    //   395: iload 19
    //   397: aload_0
    //   398: iload 22
    //   400: iload 20
    //   402: iload 23
    //   404: invokespecial 72	org/bouncycastle2/crypto/digests/RIPEMD160Digest:f1	(III)I
    //   407: iadd
    //   408: aload_0
    //   409: getfield 21	org/bouncycastle2/crypto/digests/RIPEMD160Digest:X	[I
    //   412: bipush 9
    //   414: iaload
    //   415: iadd
    //   416: bipush 13
    //   418: invokespecial 74	org/bouncycastle2/crypto/digests/RIPEMD160Digest:RL	(II)I
    //   421: iadd
    //   422: istore 24
    //   424: aload_0
    //   425: iload 20
    //   427: bipush 10
    //   429: invokespecial 74	org/bouncycastle2/crypto/digests/RIPEMD160Digest:RL	(II)I
    //   432: istore 25
    //   434: iload 23
    //   436: aload_0
    //   437: iload 21
    //   439: aload_0
    //   440: iload 24
    //   442: iload 22
    //   444: iload 25
    //   446: invokespecial 72	org/bouncycastle2/crypto/digests/RIPEMD160Digest:f1	(III)I
    //   449: iadd
    //   450: aload_0
    //   451: getfield 21	org/bouncycastle2/crypto/digests/RIPEMD160Digest:X	[I
    //   454: bipush 10
    //   456: iaload
    //   457: iadd
    //   458: bipush 14
    //   460: invokespecial 74	org/bouncycastle2/crypto/digests/RIPEMD160Digest:RL	(II)I
    //   463: iadd
    //   464: istore 26
    //   466: aload_0
    //   467: iload 22
    //   469: bipush 10
    //   471: invokespecial 74	org/bouncycastle2/crypto/digests/RIPEMD160Digest:RL	(II)I
    //   474: istore 27
    //   476: iload 25
    //   478: aload_0
    //   479: iload 23
    //   481: aload_0
    //   482: iload 26
    //   484: iload 24
    //   486: iload 27
    //   488: invokespecial 72	org/bouncycastle2/crypto/digests/RIPEMD160Digest:f1	(III)I
    //   491: iadd
    //   492: aload_0
    //   493: getfield 21	org/bouncycastle2/crypto/digests/RIPEMD160Digest:X	[I
    //   496: bipush 11
    //   498: iaload
    //   499: iadd
    //   500: bipush 15
    //   502: invokespecial 74	org/bouncycastle2/crypto/digests/RIPEMD160Digest:RL	(II)I
    //   505: iadd
    //   506: istore 28
    //   508: aload_0
    //   509: iload 24
    //   511: bipush 10
    //   513: invokespecial 74	org/bouncycastle2/crypto/digests/RIPEMD160Digest:RL	(II)I
    //   516: istore 29
    //   518: iload 27
    //   520: aload_0
    //   521: iload 25
    //   523: aload_0
    //   524: iload 28
    //   526: iload 26
    //   528: iload 29
    //   530: invokespecial 72	org/bouncycastle2/crypto/digests/RIPEMD160Digest:f1	(III)I
    //   533: iadd
    //   534: aload_0
    //   535: getfield 21	org/bouncycastle2/crypto/digests/RIPEMD160Digest:X	[I
    //   538: bipush 12
    //   540: iaload
    //   541: iadd
    //   542: bipush 6
    //   544: invokespecial 74	org/bouncycastle2/crypto/digests/RIPEMD160Digest:RL	(II)I
    //   547: iadd
    //   548: istore 30
    //   550: aload_0
    //   551: iload 26
    //   553: bipush 10
    //   555: invokespecial 74	org/bouncycastle2/crypto/digests/RIPEMD160Digest:RL	(II)I
    //   558: istore 31
    //   560: iload 29
    //   562: aload_0
    //   563: iload 27
    //   565: aload_0
    //   566: iload 30
    //   568: iload 28
    //   570: iload 31
    //   572: invokespecial 72	org/bouncycastle2/crypto/digests/RIPEMD160Digest:f1	(III)I
    //   575: iadd
    //   576: aload_0
    //   577: getfield 21	org/bouncycastle2/crypto/digests/RIPEMD160Digest:X	[I
    //   580: bipush 13
    //   582: iaload
    //   583: iadd
    //   584: bipush 7
    //   586: invokespecial 74	org/bouncycastle2/crypto/digests/RIPEMD160Digest:RL	(II)I
    //   589: iadd
    //   590: istore 32
    //   592: aload_0
    //   593: iload 28
    //   595: bipush 10
    //   597: invokespecial 74	org/bouncycastle2/crypto/digests/RIPEMD160Digest:RL	(II)I
    //   600: istore 33
    //   602: iload 31
    //   604: aload_0
    //   605: iload 29
    //   607: aload_0
    //   608: iload 32
    //   610: iload 30
    //   612: iload 33
    //   614: invokespecial 72	org/bouncycastle2/crypto/digests/RIPEMD160Digest:f1	(III)I
    //   617: iadd
    //   618: aload_0
    //   619: getfield 21	org/bouncycastle2/crypto/digests/RIPEMD160Digest:X	[I
    //   622: bipush 14
    //   624: iaload
    //   625: iadd
    //   626: bipush 9
    //   628: invokespecial 74	org/bouncycastle2/crypto/digests/RIPEMD160Digest:RL	(II)I
    //   631: iadd
    //   632: istore 34
    //   634: aload_0
    //   635: iload 30
    //   637: bipush 10
    //   639: invokespecial 74	org/bouncycastle2/crypto/digests/RIPEMD160Digest:RL	(II)I
    //   642: istore 35
    //   644: iload 33
    //   646: aload_0
    //   647: iload 31
    //   649: aload_0
    //   650: iload 34
    //   652: iload 32
    //   654: iload 35
    //   656: invokespecial 72	org/bouncycastle2/crypto/digests/RIPEMD160Digest:f1	(III)I
    //   659: iadd
    //   660: aload_0
    //   661: getfield 21	org/bouncycastle2/crypto/digests/RIPEMD160Digest:X	[I
    //   664: bipush 15
    //   666: iaload
    //   667: iadd
    //   668: bipush 8
    //   670: invokespecial 74	org/bouncycastle2/crypto/digests/RIPEMD160Digest:RL	(II)I
    //   673: iadd
    //   674: istore 36
    //   676: aload_0
    //   677: iload 32
    //   679: bipush 10
    //   681: invokespecial 74	org/bouncycastle2/crypto/digests/RIPEMD160Digest:RL	(II)I
    //   684: istore 37
    //   686: iload 5
    //   688: aload_0
    //   689: ldc 75
    //   691: iload_1
    //   692: aload_0
    //   693: iload_2
    //   694: iload_3
    //   695: iload 4
    //   697: invokespecial 77	org/bouncycastle2/crypto/digests/RIPEMD160Digest:f5	(III)I
    //   700: iadd
    //   701: aload_0
    //   702: getfield 21	org/bouncycastle2/crypto/digests/RIPEMD160Digest:X	[I
    //   705: iconst_5
    //   706: iaload
    //   707: iadd
    //   708: iadd
    //   709: bipush 8
    //   711: invokespecial 74	org/bouncycastle2/crypto/digests/RIPEMD160Digest:RL	(II)I
    //   714: iadd
    //   715: istore 38
    //   717: aload_0
    //   718: iload_3
    //   719: bipush 10
    //   721: invokespecial 74	org/bouncycastle2/crypto/digests/RIPEMD160Digest:RL	(II)I
    //   724: istore 39
    //   726: iload 4
    //   728: aload_0
    //   729: ldc 75
    //   731: iload 5
    //   733: aload_0
    //   734: iload 38
    //   736: iload_2
    //   737: iload 39
    //   739: invokespecial 77	org/bouncycastle2/crypto/digests/RIPEMD160Digest:f5	(III)I
    //   742: iadd
    //   743: aload_0
    //   744: getfield 21	org/bouncycastle2/crypto/digests/RIPEMD160Digest:X	[I
    //   747: bipush 14
    //   749: iaload
    //   750: iadd
    //   751: iadd
    //   752: bipush 9
    //   754: invokespecial 74	org/bouncycastle2/crypto/digests/RIPEMD160Digest:RL	(II)I
    //   757: iadd
    //   758: istore 40
    //   760: aload_0
    //   761: iload_2
    //   762: bipush 10
    //   764: invokespecial 74	org/bouncycastle2/crypto/digests/RIPEMD160Digest:RL	(II)I
    //   767: istore 41
    //   769: iload 39
    //   771: aload_0
    //   772: ldc 75
    //   774: iload 4
    //   776: aload_0
    //   777: iload 40
    //   779: iload 38
    //   781: iload 41
    //   783: invokespecial 77	org/bouncycastle2/crypto/digests/RIPEMD160Digest:f5	(III)I
    //   786: iadd
    //   787: aload_0
    //   788: getfield 21	org/bouncycastle2/crypto/digests/RIPEMD160Digest:X	[I
    //   791: bipush 7
    //   793: iaload
    //   794: iadd
    //   795: iadd
    //   796: bipush 9
    //   798: invokespecial 74	org/bouncycastle2/crypto/digests/RIPEMD160Digest:RL	(II)I
    //   801: iadd
    //   802: istore 42
    //   804: aload_0
    //   805: iload 38
    //   807: bipush 10
    //   809: invokespecial 74	org/bouncycastle2/crypto/digests/RIPEMD160Digest:RL	(II)I
    //   812: istore 43
    //   814: iload 41
    //   816: aload_0
    //   817: ldc 75
    //   819: iload 39
    //   821: aload_0
    //   822: iload 42
    //   824: iload 40
    //   826: iload 43
    //   828: invokespecial 77	org/bouncycastle2/crypto/digests/RIPEMD160Digest:f5	(III)I
    //   831: iadd
    //   832: aload_0
    //   833: getfield 21	org/bouncycastle2/crypto/digests/RIPEMD160Digest:X	[I
    //   836: iconst_0
    //   837: iaload
    //   838: iadd
    //   839: iadd
    //   840: bipush 11
    //   842: invokespecial 74	org/bouncycastle2/crypto/digests/RIPEMD160Digest:RL	(II)I
    //   845: iadd
    //   846: istore 44
    //   848: aload_0
    //   849: iload 40
    //   851: bipush 10
    //   853: invokespecial 74	org/bouncycastle2/crypto/digests/RIPEMD160Digest:RL	(II)I
    //   856: istore 45
    //   858: iload 43
    //   860: aload_0
    //   861: ldc 75
    //   863: iload 41
    //   865: aload_0
    //   866: iload 44
    //   868: iload 42
    //   870: iload 45
    //   872: invokespecial 77	org/bouncycastle2/crypto/digests/RIPEMD160Digest:f5	(III)I
    //   875: iadd
    //   876: aload_0
    //   877: getfield 21	org/bouncycastle2/crypto/digests/RIPEMD160Digest:X	[I
    //   880: bipush 9
    //   882: iaload
    //   883: iadd
    //   884: iadd
    //   885: bipush 13
    //   887: invokespecial 74	org/bouncycastle2/crypto/digests/RIPEMD160Digest:RL	(II)I
    //   890: iadd
    //   891: istore 46
    //   893: aload_0
    //   894: iload 42
    //   896: bipush 10
    //   898: invokespecial 74	org/bouncycastle2/crypto/digests/RIPEMD160Digest:RL	(II)I
    //   901: istore 47
    //   903: iload 45
    //   905: aload_0
    //   906: ldc 75
    //   908: iload 43
    //   910: aload_0
    //   911: iload 46
    //   913: iload 44
    //   915: iload 47
    //   917: invokespecial 77	org/bouncycastle2/crypto/digests/RIPEMD160Digest:f5	(III)I
    //   920: iadd
    //   921: aload_0
    //   922: getfield 21	org/bouncycastle2/crypto/digests/RIPEMD160Digest:X	[I
    //   925: iconst_2
    //   926: iaload
    //   927: iadd
    //   928: iadd
    //   929: bipush 15
    //   931: invokespecial 74	org/bouncycastle2/crypto/digests/RIPEMD160Digest:RL	(II)I
    //   934: iadd
    //   935: istore 48
    //   937: aload_0
    //   938: iload 44
    //   940: bipush 10
    //   942: invokespecial 74	org/bouncycastle2/crypto/digests/RIPEMD160Digest:RL	(II)I
    //   945: istore 49
    //   947: iload 47
    //   949: aload_0
    //   950: ldc 75
    //   952: iload 45
    //   954: aload_0
    //   955: iload 48
    //   957: iload 46
    //   959: iload 49
    //   961: invokespecial 77	org/bouncycastle2/crypto/digests/RIPEMD160Digest:f5	(III)I
    //   964: iadd
    //   965: aload_0
    //   966: getfield 21	org/bouncycastle2/crypto/digests/RIPEMD160Digest:X	[I
    //   969: bipush 11
    //   971: iaload
    //   972: iadd
    //   973: iadd
    //   974: bipush 15
    //   976: invokespecial 74	org/bouncycastle2/crypto/digests/RIPEMD160Digest:RL	(II)I
    //   979: iadd
    //   980: istore 50
    //   982: aload_0
    //   983: iload 46
    //   985: bipush 10
    //   987: invokespecial 74	org/bouncycastle2/crypto/digests/RIPEMD160Digest:RL	(II)I
    //   990: istore 51
    //   992: iload 49
    //   994: aload_0
    //   995: ldc 75
    //   997: iload 47
    //   999: aload_0
    //   1000: iload 50
    //   1002: iload 48
    //   1004: iload 51
    //   1006: invokespecial 77	org/bouncycastle2/crypto/digests/RIPEMD160Digest:f5	(III)I
    //   1009: iadd
    //   1010: aload_0
    //   1011: getfield 21	org/bouncycastle2/crypto/digests/RIPEMD160Digest:X	[I
    //   1014: iconst_4
    //   1015: iaload
    //   1016: iadd
    //   1017: iadd
    //   1018: iconst_5
    //   1019: invokespecial 74	org/bouncycastle2/crypto/digests/RIPEMD160Digest:RL	(II)I
    //   1022: iadd
    //   1023: istore 52
    //   1025: aload_0
    //   1026: iload 48
    //   1028: bipush 10
    //   1030: invokespecial 74	org/bouncycastle2/crypto/digests/RIPEMD160Digest:RL	(II)I
    //   1033: istore 53
    //   1035: iload 51
    //   1037: aload_0
    //   1038: ldc 75
    //   1040: iload 49
    //   1042: aload_0
    //   1043: iload 52
    //   1045: iload 50
    //   1047: iload 53
    //   1049: invokespecial 77	org/bouncycastle2/crypto/digests/RIPEMD160Digest:f5	(III)I
    //   1052: iadd
    //   1053: aload_0
    //   1054: getfield 21	org/bouncycastle2/crypto/digests/RIPEMD160Digest:X	[I
    //   1057: bipush 13
    //   1059: iaload
    //   1060: iadd
    //   1061: iadd
    //   1062: bipush 7
    //   1064: invokespecial 74	org/bouncycastle2/crypto/digests/RIPEMD160Digest:RL	(II)I
    //   1067: iadd
    //   1068: istore 54
    //   1070: aload_0
    //   1071: iload 50
    //   1073: bipush 10
    //   1075: invokespecial 74	org/bouncycastle2/crypto/digests/RIPEMD160Digest:RL	(II)I
    //   1078: istore 55
    //   1080: iload 53
    //   1082: aload_0
    //   1083: ldc 75
    //   1085: iload 51
    //   1087: aload_0
    //   1088: iload 54
    //   1090: iload 52
    //   1092: iload 55
    //   1094: invokespecial 77	org/bouncycastle2/crypto/digests/RIPEMD160Digest:f5	(III)I
    //   1097: iadd
    //   1098: aload_0
    //   1099: getfield 21	org/bouncycastle2/crypto/digests/RIPEMD160Digest:X	[I
    //   1102: bipush 6
    //   1104: iaload
    //   1105: iadd
    //   1106: iadd
    //   1107: bipush 7
    //   1109: invokespecial 74	org/bouncycastle2/crypto/digests/RIPEMD160Digest:RL	(II)I
    //   1112: iadd
    //   1113: istore 56
    //   1115: aload_0
    //   1116: iload 52
    //   1118: bipush 10
    //   1120: invokespecial 74	org/bouncycastle2/crypto/digests/RIPEMD160Digest:RL	(II)I
    //   1123: istore 57
    //   1125: iload 55
    //   1127: aload_0
    //   1128: ldc 75
    //   1130: iload 53
    //   1132: aload_0
    //   1133: iload 56
    //   1135: iload 54
    //   1137: iload 57
    //   1139: invokespecial 77	org/bouncycastle2/crypto/digests/RIPEMD160Digest:f5	(III)I
    //   1142: iadd
    //   1143: aload_0
    //   1144: getfield 21	org/bouncycastle2/crypto/digests/RIPEMD160Digest:X	[I
    //   1147: bipush 15
    //   1149: iaload
    //   1150: iadd
    //   1151: iadd
    //   1152: bipush 8
    //   1154: invokespecial 74	org/bouncycastle2/crypto/digests/RIPEMD160Digest:RL	(II)I
    //   1157: iadd
    //   1158: istore 58
    //   1160: aload_0
    //   1161: iload 54
    //   1163: bipush 10
    //   1165: invokespecial 74	org/bouncycastle2/crypto/digests/RIPEMD160Digest:RL	(II)I
    //   1168: istore 59
    //   1170: iload 57
    //   1172: aload_0
    //   1173: ldc 75
    //   1175: iload 55
    //   1177: aload_0
    //   1178: iload 58
    //   1180: iload 56
    //   1182: iload 59
    //   1184: invokespecial 77	org/bouncycastle2/crypto/digests/RIPEMD160Digest:f5	(III)I
    //   1187: iadd
    //   1188: aload_0
    //   1189: getfield 21	org/bouncycastle2/crypto/digests/RIPEMD160Digest:X	[I
    //   1192: bipush 8
    //   1194: iaload
    //   1195: iadd
    //   1196: iadd
    //   1197: bipush 11
    //   1199: invokespecial 74	org/bouncycastle2/crypto/digests/RIPEMD160Digest:RL	(II)I
    //   1202: iadd
    //   1203: istore 60
    //   1205: aload_0
    //   1206: iload 56
    //   1208: bipush 10
    //   1210: invokespecial 74	org/bouncycastle2/crypto/digests/RIPEMD160Digest:RL	(II)I
    //   1213: istore 61
    //   1215: iload 59
    //   1217: aload_0
    //   1218: ldc 75
    //   1220: iload 57
    //   1222: aload_0
    //   1223: iload 60
    //   1225: iload 58
    //   1227: iload 61
    //   1229: invokespecial 77	org/bouncycastle2/crypto/digests/RIPEMD160Digest:f5	(III)I
    //   1232: iadd
    //   1233: aload_0
    //   1234: getfield 21	org/bouncycastle2/crypto/digests/RIPEMD160Digest:X	[I
    //   1237: iconst_1
    //   1238: iaload
    //   1239: iadd
    //   1240: iadd
    //   1241: bipush 14
    //   1243: invokespecial 74	org/bouncycastle2/crypto/digests/RIPEMD160Digest:RL	(II)I
    //   1246: iadd
    //   1247: istore 62
    //   1249: aload_0
    //   1250: iload 58
    //   1252: bipush 10
    //   1254: invokespecial 74	org/bouncycastle2/crypto/digests/RIPEMD160Digest:RL	(II)I
    //   1257: istore 63
    //   1259: iload 61
    //   1261: aload_0
    //   1262: ldc 75
    //   1264: iload 59
    //   1266: aload_0
    //   1267: iload 62
    //   1269: iload 60
    //   1271: iload 63
    //   1273: invokespecial 77	org/bouncycastle2/crypto/digests/RIPEMD160Digest:f5	(III)I
    //   1276: iadd
    //   1277: aload_0
    //   1278: getfield 21	org/bouncycastle2/crypto/digests/RIPEMD160Digest:X	[I
    //   1281: bipush 10
    //   1283: iaload
    //   1284: iadd
    //   1285: iadd
    //   1286: bipush 14
    //   1288: invokespecial 74	org/bouncycastle2/crypto/digests/RIPEMD160Digest:RL	(II)I
    //   1291: iadd
    //   1292: istore 64
    //   1294: aload_0
    //   1295: iload 60
    //   1297: bipush 10
    //   1299: invokespecial 74	org/bouncycastle2/crypto/digests/RIPEMD160Digest:RL	(II)I
    //   1302: istore 65
    //   1304: iload 63
    //   1306: aload_0
    //   1307: ldc 75
    //   1309: iload 61
    //   1311: aload_0
    //   1312: iload 64
    //   1314: iload 62
    //   1316: iload 65
    //   1318: invokespecial 77	org/bouncycastle2/crypto/digests/RIPEMD160Digest:f5	(III)I
    //   1321: iadd
    //   1322: aload_0
    //   1323: getfield 21	org/bouncycastle2/crypto/digests/RIPEMD160Digest:X	[I
    //   1326: iconst_3
    //   1327: iaload
    //   1328: iadd
    //   1329: iadd
    //   1330: bipush 12
    //   1332: invokespecial 74	org/bouncycastle2/crypto/digests/RIPEMD160Digest:RL	(II)I
    //   1335: iadd
    //   1336: istore 66
    //   1338: aload_0
    //   1339: iload 62
    //   1341: bipush 10
    //   1343: invokespecial 74	org/bouncycastle2/crypto/digests/RIPEMD160Digest:RL	(II)I
    //   1346: istore 67
    //   1348: iload 65
    //   1350: aload_0
    //   1351: ldc 75
    //   1353: iload 63
    //   1355: aload_0
    //   1356: iload 66
    //   1358: iload 64
    //   1360: iload 67
    //   1362: invokespecial 77	org/bouncycastle2/crypto/digests/RIPEMD160Digest:f5	(III)I
    //   1365: iadd
    //   1366: aload_0
    //   1367: getfield 21	org/bouncycastle2/crypto/digests/RIPEMD160Digest:X	[I
    //   1370: bipush 12
    //   1372: iaload
    //   1373: iadd
    //   1374: iadd
    //   1375: bipush 6
    //   1377: invokespecial 74	org/bouncycastle2/crypto/digests/RIPEMD160Digest:RL	(II)I
    //   1380: iadd
    //   1381: istore 68
    //   1383: aload_0
    //   1384: iload 64
    //   1386: bipush 10
    //   1388: invokespecial 74	org/bouncycastle2/crypto/digests/RIPEMD160Digest:RL	(II)I
    //   1391: istore 69
    //   1393: iload 35
    //   1395: aload_0
    //   1396: ldc 78
    //   1398: iload 33
    //   1400: aload_0
    //   1401: iload 36
    //   1403: iload 34
    //   1405: iload 37
    //   1407: invokespecial 80	org/bouncycastle2/crypto/digests/RIPEMD160Digest:f2	(III)I
    //   1410: iadd
    //   1411: aload_0
    //   1412: getfield 21	org/bouncycastle2/crypto/digests/RIPEMD160Digest:X	[I
    //   1415: bipush 7
    //   1417: iaload
    //   1418: iadd
    //   1419: iadd
    //   1420: bipush 7
    //   1422: invokespecial 74	org/bouncycastle2/crypto/digests/RIPEMD160Digest:RL	(II)I
    //   1425: iadd
    //   1426: istore 70
    //   1428: aload_0
    //   1429: iload 34
    //   1431: bipush 10
    //   1433: invokespecial 74	org/bouncycastle2/crypto/digests/RIPEMD160Digest:RL	(II)I
    //   1436: istore 71
    //   1438: iload 37
    //   1440: aload_0
    //   1441: ldc 78
    //   1443: iload 35
    //   1445: aload_0
    //   1446: iload 70
    //   1448: iload 36
    //   1450: iload 71
    //   1452: invokespecial 80	org/bouncycastle2/crypto/digests/RIPEMD160Digest:f2	(III)I
    //   1455: iadd
    //   1456: aload_0
    //   1457: getfield 21	org/bouncycastle2/crypto/digests/RIPEMD160Digest:X	[I
    //   1460: iconst_4
    //   1461: iaload
    //   1462: iadd
    //   1463: iadd
    //   1464: bipush 6
    //   1466: invokespecial 74	org/bouncycastle2/crypto/digests/RIPEMD160Digest:RL	(II)I
    //   1469: iadd
    //   1470: istore 72
    //   1472: aload_0
    //   1473: iload 36
    //   1475: bipush 10
    //   1477: invokespecial 74	org/bouncycastle2/crypto/digests/RIPEMD160Digest:RL	(II)I
    //   1480: istore 73
    //   1482: iload 71
    //   1484: aload_0
    //   1485: ldc 78
    //   1487: iload 37
    //   1489: aload_0
    //   1490: iload 72
    //   1492: iload 70
    //   1494: iload 73
    //   1496: invokespecial 80	org/bouncycastle2/crypto/digests/RIPEMD160Digest:f2	(III)I
    //   1499: iadd
    //   1500: aload_0
    //   1501: getfield 21	org/bouncycastle2/crypto/digests/RIPEMD160Digest:X	[I
    //   1504: bipush 13
    //   1506: iaload
    //   1507: iadd
    //   1508: iadd
    //   1509: bipush 8
    //   1511: invokespecial 74	org/bouncycastle2/crypto/digests/RIPEMD160Digest:RL	(II)I
    //   1514: iadd
    //   1515: istore 74
    //   1517: aload_0
    //   1518: iload 70
    //   1520: bipush 10
    //   1522: invokespecial 74	org/bouncycastle2/crypto/digests/RIPEMD160Digest:RL	(II)I
    //   1525: istore 75
    //   1527: iload 73
    //   1529: aload_0
    //   1530: ldc 78
    //   1532: iload 71
    //   1534: aload_0
    //   1535: iload 74
    //   1537: iload 72
    //   1539: iload 75
    //   1541: invokespecial 80	org/bouncycastle2/crypto/digests/RIPEMD160Digest:f2	(III)I
    //   1544: iadd
    //   1545: aload_0
    //   1546: getfield 21	org/bouncycastle2/crypto/digests/RIPEMD160Digest:X	[I
    //   1549: iconst_1
    //   1550: iaload
    //   1551: iadd
    //   1552: iadd
    //   1553: bipush 13
    //   1555: invokespecial 74	org/bouncycastle2/crypto/digests/RIPEMD160Digest:RL	(II)I
    //   1558: iadd
    //   1559: istore 76
    //   1561: aload_0
    //   1562: iload 72
    //   1564: bipush 10
    //   1566: invokespecial 74	org/bouncycastle2/crypto/digests/RIPEMD160Digest:RL	(II)I
    //   1569: istore 77
    //   1571: iload 75
    //   1573: aload_0
    //   1574: ldc 78
    //   1576: iload 73
    //   1578: aload_0
    //   1579: iload 76
    //   1581: iload 74
    //   1583: iload 77
    //   1585: invokespecial 80	org/bouncycastle2/crypto/digests/RIPEMD160Digest:f2	(III)I
    //   1588: iadd
    //   1589: aload_0
    //   1590: getfield 21	org/bouncycastle2/crypto/digests/RIPEMD160Digest:X	[I
    //   1593: bipush 10
    //   1595: iaload
    //   1596: iadd
    //   1597: iadd
    //   1598: bipush 11
    //   1600: invokespecial 74	org/bouncycastle2/crypto/digests/RIPEMD160Digest:RL	(II)I
    //   1603: iadd
    //   1604: istore 78
    //   1606: aload_0
    //   1607: iload 74
    //   1609: bipush 10
    //   1611: invokespecial 74	org/bouncycastle2/crypto/digests/RIPEMD160Digest:RL	(II)I
    //   1614: istore 79
    //   1616: iload 77
    //   1618: aload_0
    //   1619: ldc 78
    //   1621: iload 75
    //   1623: aload_0
    //   1624: iload 78
    //   1626: iload 76
    //   1628: iload 79
    //   1630: invokespecial 80	org/bouncycastle2/crypto/digests/RIPEMD160Digest:f2	(III)I
    //   1633: iadd
    //   1634: aload_0
    //   1635: getfield 21	org/bouncycastle2/crypto/digests/RIPEMD160Digest:X	[I
    //   1638: bipush 6
    //   1640: iaload
    //   1641: iadd
    //   1642: iadd
    //   1643: bipush 9
    //   1645: invokespecial 74	org/bouncycastle2/crypto/digests/RIPEMD160Digest:RL	(II)I
    //   1648: iadd
    //   1649: istore 80
    //   1651: aload_0
    //   1652: iload 76
    //   1654: bipush 10
    //   1656: invokespecial 74	org/bouncycastle2/crypto/digests/RIPEMD160Digest:RL	(II)I
    //   1659: istore 81
    //   1661: iload 79
    //   1663: aload_0
    //   1664: ldc 78
    //   1666: iload 77
    //   1668: aload_0
    //   1669: iload 80
    //   1671: iload 78
    //   1673: iload 81
    //   1675: invokespecial 80	org/bouncycastle2/crypto/digests/RIPEMD160Digest:f2	(III)I
    //   1678: iadd
    //   1679: aload_0
    //   1680: getfield 21	org/bouncycastle2/crypto/digests/RIPEMD160Digest:X	[I
    //   1683: bipush 15
    //   1685: iaload
    //   1686: iadd
    //   1687: iadd
    //   1688: bipush 7
    //   1690: invokespecial 74	org/bouncycastle2/crypto/digests/RIPEMD160Digest:RL	(II)I
    //   1693: iadd
    //   1694: istore 82
    //   1696: aload_0
    //   1697: iload 78
    //   1699: bipush 10
    //   1701: invokespecial 74	org/bouncycastle2/crypto/digests/RIPEMD160Digest:RL	(II)I
    //   1704: istore 83
    //   1706: iload 81
    //   1708: aload_0
    //   1709: ldc 78
    //   1711: iload 79
    //   1713: aload_0
    //   1714: iload 82
    //   1716: iload 80
    //   1718: iload 83
    //   1720: invokespecial 80	org/bouncycastle2/crypto/digests/RIPEMD160Digest:f2	(III)I
    //   1723: iadd
    //   1724: aload_0
    //   1725: getfield 21	org/bouncycastle2/crypto/digests/RIPEMD160Digest:X	[I
    //   1728: iconst_3
    //   1729: iaload
    //   1730: iadd
    //   1731: iadd
    //   1732: bipush 15
    //   1734: invokespecial 74	org/bouncycastle2/crypto/digests/RIPEMD160Digest:RL	(II)I
    //   1737: iadd
    //   1738: istore 84
    //   1740: aload_0
    //   1741: iload 80
    //   1743: bipush 10
    //   1745: invokespecial 74	org/bouncycastle2/crypto/digests/RIPEMD160Digest:RL	(II)I
    //   1748: istore 85
    //   1750: iload 83
    //   1752: aload_0
    //   1753: ldc 78
    //   1755: iload 81
    //   1757: aload_0
    //   1758: iload 84
    //   1760: iload 82
    //   1762: iload 85
    //   1764: invokespecial 80	org/bouncycastle2/crypto/digests/RIPEMD160Digest:f2	(III)I
    //   1767: iadd
    //   1768: aload_0
    //   1769: getfield 21	org/bouncycastle2/crypto/digests/RIPEMD160Digest:X	[I
    //   1772: bipush 12
    //   1774: iaload
    //   1775: iadd
    //   1776: iadd
    //   1777: bipush 7
    //   1779: invokespecial 74	org/bouncycastle2/crypto/digests/RIPEMD160Digest:RL	(II)I
    //   1782: iadd
    //   1783: istore 86
    //   1785: aload_0
    //   1786: iload 82
    //   1788: bipush 10
    //   1790: invokespecial 74	org/bouncycastle2/crypto/digests/RIPEMD160Digest:RL	(II)I
    //   1793: istore 87
    //   1795: iload 85
    //   1797: aload_0
    //   1798: ldc 78
    //   1800: iload 83
    //   1802: aload_0
    //   1803: iload 86
    //   1805: iload 84
    //   1807: iload 87
    //   1809: invokespecial 80	org/bouncycastle2/crypto/digests/RIPEMD160Digest:f2	(III)I
    //   1812: iadd
    //   1813: aload_0
    //   1814: getfield 21	org/bouncycastle2/crypto/digests/RIPEMD160Digest:X	[I
    //   1817: iconst_0
    //   1818: iaload
    //   1819: iadd
    //   1820: iadd
    //   1821: bipush 12
    //   1823: invokespecial 74	org/bouncycastle2/crypto/digests/RIPEMD160Digest:RL	(II)I
    //   1826: iadd
    //   1827: istore 88
    //   1829: aload_0
    //   1830: iload 84
    //   1832: bipush 10
    //   1834: invokespecial 74	org/bouncycastle2/crypto/digests/RIPEMD160Digest:RL	(II)I
    //   1837: istore 89
    //   1839: iload 87
    //   1841: aload_0
    //   1842: ldc 78
    //   1844: iload 85
    //   1846: aload_0
    //   1847: iload 88
    //   1849: iload 86
    //   1851: iload 89
    //   1853: invokespecial 80	org/bouncycastle2/crypto/digests/RIPEMD160Digest:f2	(III)I
    //   1856: iadd
    //   1857: aload_0
    //   1858: getfield 21	org/bouncycastle2/crypto/digests/RIPEMD160Digest:X	[I
    //   1861: bipush 9
    //   1863: iaload
    //   1864: iadd
    //   1865: iadd
    //   1866: bipush 15
    //   1868: invokespecial 74	org/bouncycastle2/crypto/digests/RIPEMD160Digest:RL	(II)I
    //   1871: iadd
    //   1872: istore 90
    //   1874: aload_0
    //   1875: iload 86
    //   1877: bipush 10
    //   1879: invokespecial 74	org/bouncycastle2/crypto/digests/RIPEMD160Digest:RL	(II)I
    //   1882: istore 91
    //   1884: iload 89
    //   1886: aload_0
    //   1887: ldc 78
    //   1889: iload 87
    //   1891: aload_0
    //   1892: iload 90
    //   1894: iload 88
    //   1896: iload 91
    //   1898: invokespecial 80	org/bouncycastle2/crypto/digests/RIPEMD160Digest:f2	(III)I
    //   1901: iadd
    //   1902: aload_0
    //   1903: getfield 21	org/bouncycastle2/crypto/digests/RIPEMD160Digest:X	[I
    //   1906: iconst_5
    //   1907: iaload
    //   1908: iadd
    //   1909: iadd
    //   1910: bipush 9
    //   1912: invokespecial 74	org/bouncycastle2/crypto/digests/RIPEMD160Digest:RL	(II)I
    //   1915: iadd
    //   1916: istore 92
    //   1918: aload_0
    //   1919: iload 88
    //   1921: bipush 10
    //   1923: invokespecial 74	org/bouncycastle2/crypto/digests/RIPEMD160Digest:RL	(II)I
    //   1926: istore 93
    //   1928: iload 91
    //   1930: aload_0
    //   1931: ldc 78
    //   1933: iload 89
    //   1935: aload_0
    //   1936: iload 92
    //   1938: iload 90
    //   1940: iload 93
    //   1942: invokespecial 80	org/bouncycastle2/crypto/digests/RIPEMD160Digest:f2	(III)I
    //   1945: iadd
    //   1946: aload_0
    //   1947: getfield 21	org/bouncycastle2/crypto/digests/RIPEMD160Digest:X	[I
    //   1950: iconst_2
    //   1951: iaload
    //   1952: iadd
    //   1953: iadd
    //   1954: bipush 11
    //   1956: invokespecial 74	org/bouncycastle2/crypto/digests/RIPEMD160Digest:RL	(II)I
    //   1959: iadd
    //   1960: istore 94
    //   1962: aload_0
    //   1963: iload 90
    //   1965: bipush 10
    //   1967: invokespecial 74	org/bouncycastle2/crypto/digests/RIPEMD160Digest:RL	(II)I
    //   1970: istore 95
    //   1972: iload 93
    //   1974: aload_0
    //   1975: ldc 78
    //   1977: iload 91
    //   1979: aload_0
    //   1980: iload 94
    //   1982: iload 92
    //   1984: iload 95
    //   1986: invokespecial 80	org/bouncycastle2/crypto/digests/RIPEMD160Digest:f2	(III)I
    //   1989: iadd
    //   1990: aload_0
    //   1991: getfield 21	org/bouncycastle2/crypto/digests/RIPEMD160Digest:X	[I
    //   1994: bipush 14
    //   1996: iaload
    //   1997: iadd
    //   1998: iadd
    //   1999: bipush 7
    //   2001: invokespecial 74	org/bouncycastle2/crypto/digests/RIPEMD160Digest:RL	(II)I
    //   2004: iadd
    //   2005: istore 96
    //   2007: aload_0
    //   2008: iload 92
    //   2010: bipush 10
    //   2012: invokespecial 74	org/bouncycastle2/crypto/digests/RIPEMD160Digest:RL	(II)I
    //   2015: istore 97
    //   2017: iload 95
    //   2019: aload_0
    //   2020: ldc 78
    //   2022: iload 93
    //   2024: aload_0
    //   2025: iload 96
    //   2027: iload 94
    //   2029: iload 97
    //   2031: invokespecial 80	org/bouncycastle2/crypto/digests/RIPEMD160Digest:f2	(III)I
    //   2034: iadd
    //   2035: aload_0
    //   2036: getfield 21	org/bouncycastle2/crypto/digests/RIPEMD160Digest:X	[I
    //   2039: bipush 11
    //   2041: iaload
    //   2042: iadd
    //   2043: iadd
    //   2044: bipush 13
    //   2046: invokespecial 74	org/bouncycastle2/crypto/digests/RIPEMD160Digest:RL	(II)I
    //   2049: iadd
    //   2050: istore 98
    //   2052: aload_0
    //   2053: iload 94
    //   2055: bipush 10
    //   2057: invokespecial 74	org/bouncycastle2/crypto/digests/RIPEMD160Digest:RL	(II)I
    //   2060: istore 99
    //   2062: iload 97
    //   2064: aload_0
    //   2065: ldc 78
    //   2067: iload 95
    //   2069: aload_0
    //   2070: iload 98
    //   2072: iload 96
    //   2074: iload 99
    //   2076: invokespecial 80	org/bouncycastle2/crypto/digests/RIPEMD160Digest:f2	(III)I
    //   2079: iadd
    //   2080: aload_0
    //   2081: getfield 21	org/bouncycastle2/crypto/digests/RIPEMD160Digest:X	[I
    //   2084: bipush 8
    //   2086: iaload
    //   2087: iadd
    //   2088: iadd
    //   2089: bipush 12
    //   2091: invokespecial 74	org/bouncycastle2/crypto/digests/RIPEMD160Digest:RL	(II)I
    //   2094: iadd
    //   2095: istore 100
    //   2097: aload_0
    //   2098: iload 96
    //   2100: bipush 10
    //   2102: invokespecial 74	org/bouncycastle2/crypto/digests/RIPEMD160Digest:RL	(II)I
    //   2105: istore 101
    //   2107: iload 67
    //   2109: aload_0
    //   2110: ldc 81
    //   2112: iload 65
    //   2114: aload_0
    //   2115: iload 68
    //   2117: iload 66
    //   2119: iload 69
    //   2121: invokespecial 83	org/bouncycastle2/crypto/digests/RIPEMD160Digest:f4	(III)I
    //   2124: iadd
    //   2125: aload_0
    //   2126: getfield 21	org/bouncycastle2/crypto/digests/RIPEMD160Digest:X	[I
    //   2129: bipush 6
    //   2131: iaload
    //   2132: iadd
    //   2133: iadd
    //   2134: bipush 9
    //   2136: invokespecial 74	org/bouncycastle2/crypto/digests/RIPEMD160Digest:RL	(II)I
    //   2139: iadd
    //   2140: istore 102
    //   2142: aload_0
    //   2143: iload 66
    //   2145: bipush 10
    //   2147: invokespecial 74	org/bouncycastle2/crypto/digests/RIPEMD160Digest:RL	(II)I
    //   2150: istore 103
    //   2152: iload 69
    //   2154: aload_0
    //   2155: ldc 81
    //   2157: iload 67
    //   2159: aload_0
    //   2160: iload 102
    //   2162: iload 68
    //   2164: iload 103
    //   2166: invokespecial 83	org/bouncycastle2/crypto/digests/RIPEMD160Digest:f4	(III)I
    //   2169: iadd
    //   2170: aload_0
    //   2171: getfield 21	org/bouncycastle2/crypto/digests/RIPEMD160Digest:X	[I
    //   2174: bipush 11
    //   2176: iaload
    //   2177: iadd
    //   2178: iadd
    //   2179: bipush 13
    //   2181: invokespecial 74	org/bouncycastle2/crypto/digests/RIPEMD160Digest:RL	(II)I
    //   2184: iadd
    //   2185: istore 104
    //   2187: aload_0
    //   2188: iload 68
    //   2190: bipush 10
    //   2192: invokespecial 74	org/bouncycastle2/crypto/digests/RIPEMD160Digest:RL	(II)I
    //   2195: istore 105
    //   2197: iload 103
    //   2199: aload_0
    //   2200: ldc 81
    //   2202: iload 69
    //   2204: aload_0
    //   2205: iload 104
    //   2207: iload 102
    //   2209: iload 105
    //   2211: invokespecial 83	org/bouncycastle2/crypto/digests/RIPEMD160Digest:f4	(III)I
    //   2214: iadd
    //   2215: aload_0
    //   2216: getfield 21	org/bouncycastle2/crypto/digests/RIPEMD160Digest:X	[I
    //   2219: iconst_3
    //   2220: iaload
    //   2221: iadd
    //   2222: iadd
    //   2223: bipush 15
    //   2225: invokespecial 74	org/bouncycastle2/crypto/digests/RIPEMD160Digest:RL	(II)I
    //   2228: iadd
    //   2229: istore 106
    //   2231: aload_0
    //   2232: iload 102
    //   2234: bipush 10
    //   2236: invokespecial 74	org/bouncycastle2/crypto/digests/RIPEMD160Digest:RL	(II)I
    //   2239: istore 107
    //   2241: iload 105
    //   2243: aload_0
    //   2244: ldc 81
    //   2246: iload 103
    //   2248: aload_0
    //   2249: iload 106
    //   2251: iload 104
    //   2253: iload 107
    //   2255: invokespecial 83	org/bouncycastle2/crypto/digests/RIPEMD160Digest:f4	(III)I
    //   2258: iadd
    //   2259: aload_0
    //   2260: getfield 21	org/bouncycastle2/crypto/digests/RIPEMD160Digest:X	[I
    //   2263: bipush 7
    //   2265: iaload
    //   2266: iadd
    //   2267: iadd
    //   2268: bipush 7
    //   2270: invokespecial 74	org/bouncycastle2/crypto/digests/RIPEMD160Digest:RL	(II)I
    //   2273: iadd
    //   2274: istore 108
    //   2276: aload_0
    //   2277: iload 104
    //   2279: bipush 10
    //   2281: invokespecial 74	org/bouncycastle2/crypto/digests/RIPEMD160Digest:RL	(II)I
    //   2284: istore 109
    //   2286: iload 107
    //   2288: aload_0
    //   2289: ldc 81
    //   2291: iload 105
    //   2293: aload_0
    //   2294: iload 108
    //   2296: iload 106
    //   2298: iload 109
    //   2300: invokespecial 83	org/bouncycastle2/crypto/digests/RIPEMD160Digest:f4	(III)I
    //   2303: iadd
    //   2304: aload_0
    //   2305: getfield 21	org/bouncycastle2/crypto/digests/RIPEMD160Digest:X	[I
    //   2308: iconst_0
    //   2309: iaload
    //   2310: iadd
    //   2311: iadd
    //   2312: bipush 12
    //   2314: invokespecial 74	org/bouncycastle2/crypto/digests/RIPEMD160Digest:RL	(II)I
    //   2317: iadd
    //   2318: istore 110
    //   2320: aload_0
    //   2321: iload 106
    //   2323: bipush 10
    //   2325: invokespecial 74	org/bouncycastle2/crypto/digests/RIPEMD160Digest:RL	(II)I
    //   2328: istore 111
    //   2330: iload 109
    //   2332: aload_0
    //   2333: ldc 81
    //   2335: iload 107
    //   2337: aload_0
    //   2338: iload 110
    //   2340: iload 108
    //   2342: iload 111
    //   2344: invokespecial 83	org/bouncycastle2/crypto/digests/RIPEMD160Digest:f4	(III)I
    //   2347: iadd
    //   2348: aload_0
    //   2349: getfield 21	org/bouncycastle2/crypto/digests/RIPEMD160Digest:X	[I
    //   2352: bipush 13
    //   2354: iaload
    //   2355: iadd
    //   2356: iadd
    //   2357: bipush 8
    //   2359: invokespecial 74	org/bouncycastle2/crypto/digests/RIPEMD160Digest:RL	(II)I
    //   2362: iadd
    //   2363: istore 112
    //   2365: aload_0
    //   2366: iload 108
    //   2368: bipush 10
    //   2370: invokespecial 74	org/bouncycastle2/crypto/digests/RIPEMD160Digest:RL	(II)I
    //   2373: istore 113
    //   2375: iload 111
    //   2377: aload_0
    //   2378: ldc 81
    //   2380: iload 109
    //   2382: aload_0
    //   2383: iload 112
    //   2385: iload 110
    //   2387: iload 113
    //   2389: invokespecial 83	org/bouncycastle2/crypto/digests/RIPEMD160Digest:f4	(III)I
    //   2392: iadd
    //   2393: aload_0
    //   2394: getfield 21	org/bouncycastle2/crypto/digests/RIPEMD160Digest:X	[I
    //   2397: iconst_5
    //   2398: iaload
    //   2399: iadd
    //   2400: iadd
    //   2401: bipush 9
    //   2403: invokespecial 74	org/bouncycastle2/crypto/digests/RIPEMD160Digest:RL	(II)I
    //   2406: iadd
    //   2407: istore 114
    //   2409: aload_0
    //   2410: iload 110
    //   2412: bipush 10
    //   2414: invokespecial 74	org/bouncycastle2/crypto/digests/RIPEMD160Digest:RL	(II)I
    //   2417: istore 115
    //   2419: iload 113
    //   2421: aload_0
    //   2422: ldc 81
    //   2424: iload 111
    //   2426: aload_0
    //   2427: iload 114
    //   2429: iload 112
    //   2431: iload 115
    //   2433: invokespecial 83	org/bouncycastle2/crypto/digests/RIPEMD160Digest:f4	(III)I
    //   2436: iadd
    //   2437: aload_0
    //   2438: getfield 21	org/bouncycastle2/crypto/digests/RIPEMD160Digest:X	[I
    //   2441: bipush 10
    //   2443: iaload
    //   2444: iadd
    //   2445: iadd
    //   2446: bipush 11
    //   2448: invokespecial 74	org/bouncycastle2/crypto/digests/RIPEMD160Digest:RL	(II)I
    //   2451: iadd
    //   2452: istore 116
    //   2454: aload_0
    //   2455: iload 112
    //   2457: bipush 10
    //   2459: invokespecial 74	org/bouncycastle2/crypto/digests/RIPEMD160Digest:RL	(II)I
    //   2462: istore 117
    //   2464: iload 115
    //   2466: aload_0
    //   2467: ldc 81
    //   2469: iload 113
    //   2471: aload_0
    //   2472: iload 116
    //   2474: iload 114
    //   2476: iload 117
    //   2478: invokespecial 83	org/bouncycastle2/crypto/digests/RIPEMD160Digest:f4	(III)I
    //   2481: iadd
    //   2482: aload_0
    //   2483: getfield 21	org/bouncycastle2/crypto/digests/RIPEMD160Digest:X	[I
    //   2486: bipush 14
    //   2488: iaload
    //   2489: iadd
    //   2490: iadd
    //   2491: bipush 7
    //   2493: invokespecial 74	org/bouncycastle2/crypto/digests/RIPEMD160Digest:RL	(II)I
    //   2496: iadd
    //   2497: istore 118
    //   2499: aload_0
    //   2500: iload 114
    //   2502: bipush 10
    //   2504: invokespecial 74	org/bouncycastle2/crypto/digests/RIPEMD160Digest:RL	(II)I
    //   2507: istore 119
    //   2509: iload 117
    //   2511: aload_0
    //   2512: ldc 81
    //   2514: iload 115
    //   2516: aload_0
    //   2517: iload 118
    //   2519: iload 116
    //   2521: iload 119
    //   2523: invokespecial 83	org/bouncycastle2/crypto/digests/RIPEMD160Digest:f4	(III)I
    //   2526: iadd
    //   2527: aload_0
    //   2528: getfield 21	org/bouncycastle2/crypto/digests/RIPEMD160Digest:X	[I
    //   2531: bipush 15
    //   2533: iaload
    //   2534: iadd
    //   2535: iadd
    //   2536: bipush 7
    //   2538: invokespecial 74	org/bouncycastle2/crypto/digests/RIPEMD160Digest:RL	(II)I
    //   2541: iadd
    //   2542: istore 120
    //   2544: aload_0
    //   2545: iload 116
    //   2547: bipush 10
    //   2549: invokespecial 74	org/bouncycastle2/crypto/digests/RIPEMD160Digest:RL	(II)I
    //   2552: istore 121
    //   2554: iload 119
    //   2556: aload_0
    //   2557: ldc 81
    //   2559: iload 117
    //   2561: aload_0
    //   2562: iload 120
    //   2564: iload 118
    //   2566: iload 121
    //   2568: invokespecial 83	org/bouncycastle2/crypto/digests/RIPEMD160Digest:f4	(III)I
    //   2571: iadd
    //   2572: aload_0
    //   2573: getfield 21	org/bouncycastle2/crypto/digests/RIPEMD160Digest:X	[I
    //   2576: bipush 8
    //   2578: iaload
    //   2579: iadd
    //   2580: iadd
    //   2581: bipush 12
    //   2583: invokespecial 74	org/bouncycastle2/crypto/digests/RIPEMD160Digest:RL	(II)I
    //   2586: iadd
    //   2587: istore 122
    //   2589: aload_0
    //   2590: iload 118
    //   2592: bipush 10
    //   2594: invokespecial 74	org/bouncycastle2/crypto/digests/RIPEMD160Digest:RL	(II)I
    //   2597: istore 123
    //   2599: iload 121
    //   2601: aload_0
    //   2602: ldc 81
    //   2604: iload 119
    //   2606: aload_0
    //   2607: iload 122
    //   2609: iload 120
    //   2611: iload 123
    //   2613: invokespecial 83	org/bouncycastle2/crypto/digests/RIPEMD160Digest:f4	(III)I
    //   2616: iadd
    //   2617: aload_0
    //   2618: getfield 21	org/bouncycastle2/crypto/digests/RIPEMD160Digest:X	[I
    //   2621: bipush 12
    //   2623: iaload
    //   2624: iadd
    //   2625: iadd
    //   2626: bipush 7
    //   2628: invokespecial 74	org/bouncycastle2/crypto/digests/RIPEMD160Digest:RL	(II)I
    //   2631: iadd
    //   2632: istore 124
    //   2634: aload_0
    //   2635: iload 120
    //   2637: bipush 10
    //   2639: invokespecial 74	org/bouncycastle2/crypto/digests/RIPEMD160Digest:RL	(II)I
    //   2642: istore 125
    //   2644: iload 123
    //   2646: aload_0
    //   2647: ldc 81
    //   2649: iload 121
    //   2651: aload_0
    //   2652: iload 124
    //   2654: iload 122
    //   2656: iload 125
    //   2658: invokespecial 83	org/bouncycastle2/crypto/digests/RIPEMD160Digest:f4	(III)I
    //   2661: iadd
    //   2662: aload_0
    //   2663: getfield 21	org/bouncycastle2/crypto/digests/RIPEMD160Digest:X	[I
    //   2666: iconst_4
    //   2667: iaload
    //   2668: iadd
    //   2669: iadd
    //   2670: bipush 6
    //   2672: invokespecial 74	org/bouncycastle2/crypto/digests/RIPEMD160Digest:RL	(II)I
    //   2675: iadd
    //   2676: istore 126
    //   2678: aload_0
    //   2679: iload 122
    //   2681: bipush 10
    //   2683: invokespecial 74	org/bouncycastle2/crypto/digests/RIPEMD160Digest:RL	(II)I
    //   2686: istore 127
    //   2688: iload 125
    //   2690: aload_0
    //   2691: ldc 81
    //   2693: iload 123
    //   2695: aload_0
    //   2696: iload 126
    //   2698: iload 124
    //   2700: iload 127
    //   2702: invokespecial 83	org/bouncycastle2/crypto/digests/RIPEMD160Digest:f4	(III)I
    //   2705: iadd
    //   2706: aload_0
    //   2707: getfield 21	org/bouncycastle2/crypto/digests/RIPEMD160Digest:X	[I
    //   2710: bipush 9
    //   2712: iaload
    //   2713: iadd
    //   2714: iadd
    //   2715: bipush 15
    //   2717: invokespecial 74	org/bouncycastle2/crypto/digests/RIPEMD160Digest:RL	(II)I
    //   2720: iadd
    //   2721: istore 128
    //   2723: aload_0
    //   2724: iload 124
    //   2726: bipush 10
    //   2728: invokespecial 74	org/bouncycastle2/crypto/digests/RIPEMD160Digest:RL	(II)I
    //   2731: istore 129
    //   2733: iload 127
    //   2735: aload_0
    //   2736: ldc 81
    //   2738: iload 125
    //   2740: aload_0
    //   2741: iload 128
    //   2743: iload 126
    //   2745: iload 129
    //   2747: invokespecial 83	org/bouncycastle2/crypto/digests/RIPEMD160Digest:f4	(III)I
    //   2750: iadd
    //   2751: aload_0
    //   2752: getfield 21	org/bouncycastle2/crypto/digests/RIPEMD160Digest:X	[I
    //   2755: iconst_1
    //   2756: iaload
    //   2757: iadd
    //   2758: iadd
    //   2759: bipush 13
    //   2761: invokespecial 74	org/bouncycastle2/crypto/digests/RIPEMD160Digest:RL	(II)I
    //   2764: iadd
    //   2765: istore 130
    //   2767: aload_0
    //   2768: iload 126
    //   2770: bipush 10
    //   2772: invokespecial 74	org/bouncycastle2/crypto/digests/RIPEMD160Digest:RL	(II)I
    //   2775: istore 131
    //   2777: iload 129
    //   2779: aload_0
    //   2780: ldc 81
    //   2782: iload 127
    //   2784: aload_0
    //   2785: iload 130
    //   2787: iload 128
    //   2789: iload 131
    //   2791: invokespecial 83	org/bouncycastle2/crypto/digests/RIPEMD160Digest:f4	(III)I
    //   2794: iadd
    //   2795: aload_0
    //   2796: getfield 21	org/bouncycastle2/crypto/digests/RIPEMD160Digest:X	[I
    //   2799: iconst_2
    //   2800: iaload
    //   2801: iadd
    //   2802: iadd
    //   2803: bipush 11
    //   2805: invokespecial 74	org/bouncycastle2/crypto/digests/RIPEMD160Digest:RL	(II)I
    //   2808: iadd
    //   2809: istore 132
    //   2811: aload_0
    //   2812: iload 128
    //   2814: bipush 10
    //   2816: invokespecial 74	org/bouncycastle2/crypto/digests/RIPEMD160Digest:RL	(II)I
    //   2819: istore 133
    //   2821: iload 99
    //   2823: aload_0
    //   2824: ldc 84
    //   2826: iload 97
    //   2828: aload_0
    //   2829: iload 100
    //   2831: iload 98
    //   2833: iload 101
    //   2835: invokespecial 86	org/bouncycastle2/crypto/digests/RIPEMD160Digest:f3	(III)I
    //   2838: iadd
    //   2839: aload_0
    //   2840: getfield 21	org/bouncycastle2/crypto/digests/RIPEMD160Digest:X	[I
    //   2843: iconst_3
    //   2844: iaload
    //   2845: iadd
    //   2846: iadd
    //   2847: bipush 11
    //   2849: invokespecial 74	org/bouncycastle2/crypto/digests/RIPEMD160Digest:RL	(II)I
    //   2852: iadd
    //   2853: istore 134
    //   2855: aload_0
    //   2856: iload 98
    //   2858: bipush 10
    //   2860: invokespecial 74	org/bouncycastle2/crypto/digests/RIPEMD160Digest:RL	(II)I
    //   2863: istore 135
    //   2865: iload 101
    //   2867: aload_0
    //   2868: ldc 84
    //   2870: iload 99
    //   2872: aload_0
    //   2873: iload 134
    //   2875: iload 100
    //   2877: iload 135
    //   2879: invokespecial 86	org/bouncycastle2/crypto/digests/RIPEMD160Digest:f3	(III)I
    //   2882: iadd
    //   2883: aload_0
    //   2884: getfield 21	org/bouncycastle2/crypto/digests/RIPEMD160Digest:X	[I
    //   2887: bipush 10
    //   2889: iaload
    //   2890: iadd
    //   2891: iadd
    //   2892: bipush 13
    //   2894: invokespecial 74	org/bouncycastle2/crypto/digests/RIPEMD160Digest:RL	(II)I
    //   2897: iadd
    //   2898: istore 136
    //   2900: aload_0
    //   2901: iload 100
    //   2903: bipush 10
    //   2905: invokespecial 74	org/bouncycastle2/crypto/digests/RIPEMD160Digest:RL	(II)I
    //   2908: istore 137
    //   2910: iload 135
    //   2912: aload_0
    //   2913: ldc 84
    //   2915: iload 101
    //   2917: aload_0
    //   2918: iload 136
    //   2920: iload 134
    //   2922: iload 137
    //   2924: invokespecial 86	org/bouncycastle2/crypto/digests/RIPEMD160Digest:f3	(III)I
    //   2927: iadd
    //   2928: aload_0
    //   2929: getfield 21	org/bouncycastle2/crypto/digests/RIPEMD160Digest:X	[I
    //   2932: bipush 14
    //   2934: iaload
    //   2935: iadd
    //   2936: iadd
    //   2937: bipush 6
    //   2939: invokespecial 74	org/bouncycastle2/crypto/digests/RIPEMD160Digest:RL	(II)I
    //   2942: iadd
    //   2943: istore 138
    //   2945: aload_0
    //   2946: iload 134
    //   2948: bipush 10
    //   2950: invokespecial 74	org/bouncycastle2/crypto/digests/RIPEMD160Digest:RL	(II)I
    //   2953: istore 139
    //   2955: iload 137
    //   2957: aload_0
    //   2958: ldc 84
    //   2960: iload 135
    //   2962: aload_0
    //   2963: iload 138
    //   2965: iload 136
    //   2967: iload 139
    //   2969: invokespecial 86	org/bouncycastle2/crypto/digests/RIPEMD160Digest:f3	(III)I
    //   2972: iadd
    //   2973: aload_0
    //   2974: getfield 21	org/bouncycastle2/crypto/digests/RIPEMD160Digest:X	[I
    //   2977: iconst_4
    //   2978: iaload
    //   2979: iadd
    //   2980: iadd
    //   2981: bipush 7
    //   2983: invokespecial 74	org/bouncycastle2/crypto/digests/RIPEMD160Digest:RL	(II)I
    //   2986: iadd
    //   2987: istore 140
    //   2989: aload_0
    //   2990: iload 136
    //   2992: bipush 10
    //   2994: invokespecial 74	org/bouncycastle2/crypto/digests/RIPEMD160Digest:RL	(II)I
    //   2997: istore 141
    //   2999: iload 139
    //   3001: aload_0
    //   3002: ldc 84
    //   3004: iload 137
    //   3006: aload_0
    //   3007: iload 140
    //   3009: iload 138
    //   3011: iload 141
    //   3013: invokespecial 86	org/bouncycastle2/crypto/digests/RIPEMD160Digest:f3	(III)I
    //   3016: iadd
    //   3017: aload_0
    //   3018: getfield 21	org/bouncycastle2/crypto/digests/RIPEMD160Digest:X	[I
    //   3021: bipush 9
    //   3023: iaload
    //   3024: iadd
    //   3025: iadd
    //   3026: bipush 14
    //   3028: invokespecial 74	org/bouncycastle2/crypto/digests/RIPEMD160Digest:RL	(II)I
    //   3031: iadd
    //   3032: istore 142
    //   3034: aload_0
    //   3035: iload 138
    //   3037: bipush 10
    //   3039: invokespecial 74	org/bouncycastle2/crypto/digests/RIPEMD160Digest:RL	(II)I
    //   3042: istore 143
    //   3044: iload 141
    //   3046: aload_0
    //   3047: ldc 84
    //   3049: iload 139
    //   3051: aload_0
    //   3052: iload 142
    //   3054: iload 140
    //   3056: iload 143
    //   3058: invokespecial 86	org/bouncycastle2/crypto/digests/RIPEMD160Digest:f3	(III)I
    //   3061: iadd
    //   3062: aload_0
    //   3063: getfield 21	org/bouncycastle2/crypto/digests/RIPEMD160Digest:X	[I
    //   3066: bipush 15
    //   3068: iaload
    //   3069: iadd
    //   3070: iadd
    //   3071: bipush 9
    //   3073: invokespecial 74	org/bouncycastle2/crypto/digests/RIPEMD160Digest:RL	(II)I
    //   3076: iadd
    //   3077: istore 144
    //   3079: aload_0
    //   3080: iload 140
    //   3082: bipush 10
    //   3084: invokespecial 74	org/bouncycastle2/crypto/digests/RIPEMD160Digest:RL	(II)I
    //   3087: istore 145
    //   3089: iload 143
    //   3091: aload_0
    //   3092: ldc 84
    //   3094: iload 141
    //   3096: aload_0
    //   3097: iload 144
    //   3099: iload 142
    //   3101: iload 145
    //   3103: invokespecial 86	org/bouncycastle2/crypto/digests/RIPEMD160Digest:f3	(III)I
    //   3106: iadd
    //   3107: aload_0
    //   3108: getfield 21	org/bouncycastle2/crypto/digests/RIPEMD160Digest:X	[I
    //   3111: bipush 8
    //   3113: iaload
    //   3114: iadd
    //   3115: iadd
    //   3116: bipush 13
    //   3118: invokespecial 74	org/bouncycastle2/crypto/digests/RIPEMD160Digest:RL	(II)I
    //   3121: iadd
    //   3122: istore 146
    //   3124: aload_0
    //   3125: iload 142
    //   3127: bipush 10
    //   3129: invokespecial 74	org/bouncycastle2/crypto/digests/RIPEMD160Digest:RL	(II)I
    //   3132: istore 147
    //   3134: iload 145
    //   3136: aload_0
    //   3137: ldc 84
    //   3139: iload 143
    //   3141: aload_0
    //   3142: iload 146
    //   3144: iload 144
    //   3146: iload 147
    //   3148: invokespecial 86	org/bouncycastle2/crypto/digests/RIPEMD160Digest:f3	(III)I
    //   3151: iadd
    //   3152: aload_0
    //   3153: getfield 21	org/bouncycastle2/crypto/digests/RIPEMD160Digest:X	[I
    //   3156: iconst_1
    //   3157: iaload
    //   3158: iadd
    //   3159: iadd
    //   3160: bipush 15
    //   3162: invokespecial 74	org/bouncycastle2/crypto/digests/RIPEMD160Digest:RL	(II)I
    //   3165: iadd
    //   3166: istore 148
    //   3168: aload_0
    //   3169: iload 144
    //   3171: bipush 10
    //   3173: invokespecial 74	org/bouncycastle2/crypto/digests/RIPEMD160Digest:RL	(II)I
    //   3176: istore 149
    //   3178: iload 147
    //   3180: aload_0
    //   3181: ldc 84
    //   3183: iload 145
    //   3185: aload_0
    //   3186: iload 148
    //   3188: iload 146
    //   3190: iload 149
    //   3192: invokespecial 86	org/bouncycastle2/crypto/digests/RIPEMD160Digest:f3	(III)I
    //   3195: iadd
    //   3196: aload_0
    //   3197: getfield 21	org/bouncycastle2/crypto/digests/RIPEMD160Digest:X	[I
    //   3200: iconst_2
    //   3201: iaload
    //   3202: iadd
    //   3203: iadd
    //   3204: bipush 14
    //   3206: invokespecial 74	org/bouncycastle2/crypto/digests/RIPEMD160Digest:RL	(II)I
    //   3209: iadd
    //   3210: istore 150
    //   3212: aload_0
    //   3213: iload 146
    //   3215: bipush 10
    //   3217: invokespecial 74	org/bouncycastle2/crypto/digests/RIPEMD160Digest:RL	(II)I
    //   3220: istore 151
    //   3222: iload 149
    //   3224: aload_0
    //   3225: ldc 84
    //   3227: iload 147
    //   3229: aload_0
    //   3230: iload 150
    //   3232: iload 148
    //   3234: iload 151
    //   3236: invokespecial 86	org/bouncycastle2/crypto/digests/RIPEMD160Digest:f3	(III)I
    //   3239: iadd
    //   3240: aload_0
    //   3241: getfield 21	org/bouncycastle2/crypto/digests/RIPEMD160Digest:X	[I
    //   3244: bipush 7
    //   3246: iaload
    //   3247: iadd
    //   3248: iadd
    //   3249: bipush 8
    //   3251: invokespecial 74	org/bouncycastle2/crypto/digests/RIPEMD160Digest:RL	(II)I
    //   3254: iadd
    //   3255: istore 152
    //   3257: aload_0
    //   3258: iload 148
    //   3260: bipush 10
    //   3262: invokespecial 74	org/bouncycastle2/crypto/digests/RIPEMD160Digest:RL	(II)I
    //   3265: istore 153
    //   3267: iload 151
    //   3269: aload_0
    //   3270: ldc 84
    //   3272: iload 149
    //   3274: aload_0
    //   3275: iload 152
    //   3277: iload 150
    //   3279: iload 153
    //   3281: invokespecial 86	org/bouncycastle2/crypto/digests/RIPEMD160Digest:f3	(III)I
    //   3284: iadd
    //   3285: aload_0
    //   3286: getfield 21	org/bouncycastle2/crypto/digests/RIPEMD160Digest:X	[I
    //   3289: iconst_0
    //   3290: iaload
    //   3291: iadd
    //   3292: iadd
    //   3293: bipush 13
    //   3295: invokespecial 74	org/bouncycastle2/crypto/digests/RIPEMD160Digest:RL	(II)I
    //   3298: iadd
    //   3299: istore 154
    //   3301: aload_0
    //   3302: iload 150
    //   3304: bipush 10
    //   3306: invokespecial 74	org/bouncycastle2/crypto/digests/RIPEMD160Digest:RL	(II)I
    //   3309: istore 155
    //   3311: iload 153
    //   3313: aload_0
    //   3314: ldc 84
    //   3316: iload 151
    //   3318: aload_0
    //   3319: iload 154
    //   3321: iload 152
    //   3323: iload 155
    //   3325: invokespecial 86	org/bouncycastle2/crypto/digests/RIPEMD160Digest:f3	(III)I
    //   3328: iadd
    //   3329: aload_0
    //   3330: getfield 21	org/bouncycastle2/crypto/digests/RIPEMD160Digest:X	[I
    //   3333: bipush 6
    //   3335: iaload
    //   3336: iadd
    //   3337: iadd
    //   3338: bipush 6
    //   3340: invokespecial 74	org/bouncycastle2/crypto/digests/RIPEMD160Digest:RL	(II)I
    //   3343: iadd
    //   3344: istore 156
    //   3346: aload_0
    //   3347: iload 152
    //   3349: bipush 10
    //   3351: invokespecial 74	org/bouncycastle2/crypto/digests/RIPEMD160Digest:RL	(II)I
    //   3354: istore 157
    //   3356: iload 155
    //   3358: aload_0
    //   3359: ldc 84
    //   3361: iload 153
    //   3363: aload_0
    //   3364: iload 156
    //   3366: iload 154
    //   3368: iload 157
    //   3370: invokespecial 86	org/bouncycastle2/crypto/digests/RIPEMD160Digest:f3	(III)I
    //   3373: iadd
    //   3374: aload_0
    //   3375: getfield 21	org/bouncycastle2/crypto/digests/RIPEMD160Digest:X	[I
    //   3378: bipush 13
    //   3380: iaload
    //   3381: iadd
    //   3382: iadd
    //   3383: iconst_5
    //   3384: invokespecial 74	org/bouncycastle2/crypto/digests/RIPEMD160Digest:RL	(II)I
    //   3387: iadd
    //   3388: istore 158
    //   3390: aload_0
    //   3391: iload 154
    //   3393: bipush 10
    //   3395: invokespecial 74	org/bouncycastle2/crypto/digests/RIPEMD160Digest:RL	(II)I
    //   3398: istore 159
    //   3400: iload 157
    //   3402: aload_0
    //   3403: ldc 84
    //   3405: iload 155
    //   3407: aload_0
    //   3408: iload 158
    //   3410: iload 156
    //   3412: iload 159
    //   3414: invokespecial 86	org/bouncycastle2/crypto/digests/RIPEMD160Digest:f3	(III)I
    //   3417: iadd
    //   3418: aload_0
    //   3419: getfield 21	org/bouncycastle2/crypto/digests/RIPEMD160Digest:X	[I
    //   3422: bipush 11
    //   3424: iaload
    //   3425: iadd
    //   3426: iadd
    //   3427: bipush 12
    //   3429: invokespecial 74	org/bouncycastle2/crypto/digests/RIPEMD160Digest:RL	(II)I
    //   3432: iadd
    //   3433: istore 160
    //   3435: aload_0
    //   3436: iload 156
    //   3438: bipush 10
    //   3440: invokespecial 74	org/bouncycastle2/crypto/digests/RIPEMD160Digest:RL	(II)I
    //   3443: istore 161
    //   3445: iload 159
    //   3447: aload_0
    //   3448: ldc 84
    //   3450: iload 157
    //   3452: aload_0
    //   3453: iload 160
    //   3455: iload 158
    //   3457: iload 161
    //   3459: invokespecial 86	org/bouncycastle2/crypto/digests/RIPEMD160Digest:f3	(III)I
    //   3462: iadd
    //   3463: aload_0
    //   3464: getfield 21	org/bouncycastle2/crypto/digests/RIPEMD160Digest:X	[I
    //   3467: iconst_5
    //   3468: iaload
    //   3469: iadd
    //   3470: iadd
    //   3471: bipush 7
    //   3473: invokespecial 74	org/bouncycastle2/crypto/digests/RIPEMD160Digest:RL	(II)I
    //   3476: iadd
    //   3477: istore 162
    //   3479: aload_0
    //   3480: iload 158
    //   3482: bipush 10
    //   3484: invokespecial 74	org/bouncycastle2/crypto/digests/RIPEMD160Digest:RL	(II)I
    //   3487: istore 163
    //   3489: iload 161
    //   3491: aload_0
    //   3492: ldc 84
    //   3494: iload 159
    //   3496: aload_0
    //   3497: iload 162
    //   3499: iload 160
    //   3501: iload 163
    //   3503: invokespecial 86	org/bouncycastle2/crypto/digests/RIPEMD160Digest:f3	(III)I
    //   3506: iadd
    //   3507: aload_0
    //   3508: getfield 21	org/bouncycastle2/crypto/digests/RIPEMD160Digest:X	[I
    //   3511: bipush 12
    //   3513: iaload
    //   3514: iadd
    //   3515: iadd
    //   3516: iconst_5
    //   3517: invokespecial 74	org/bouncycastle2/crypto/digests/RIPEMD160Digest:RL	(II)I
    //   3520: iadd
    //   3521: istore 164
    //   3523: aload_0
    //   3524: iload 160
    //   3526: bipush 10
    //   3528: invokespecial 74	org/bouncycastle2/crypto/digests/RIPEMD160Digest:RL	(II)I
    //   3531: istore 165
    //   3533: iload 131
    //   3535: aload_0
    //   3536: ldc 87
    //   3538: iload 129
    //   3540: aload_0
    //   3541: iload 132
    //   3543: iload 130
    //   3545: iload 133
    //   3547: invokespecial 86	org/bouncycastle2/crypto/digests/RIPEMD160Digest:f3	(III)I
    //   3550: iadd
    //   3551: aload_0
    //   3552: getfield 21	org/bouncycastle2/crypto/digests/RIPEMD160Digest:X	[I
    //   3555: bipush 15
    //   3557: iaload
    //   3558: iadd
    //   3559: iadd
    //   3560: bipush 9
    //   3562: invokespecial 74	org/bouncycastle2/crypto/digests/RIPEMD160Digest:RL	(II)I
    //   3565: iadd
    //   3566: istore 166
    //   3568: aload_0
    //   3569: iload 130
    //   3571: bipush 10
    //   3573: invokespecial 74	org/bouncycastle2/crypto/digests/RIPEMD160Digest:RL	(II)I
    //   3576: istore 167
    //   3578: iload 133
    //   3580: aload_0
    //   3581: ldc 87
    //   3583: iload 131
    //   3585: aload_0
    //   3586: iload 166
    //   3588: iload 132
    //   3590: iload 167
    //   3592: invokespecial 86	org/bouncycastle2/crypto/digests/RIPEMD160Digest:f3	(III)I
    //   3595: iadd
    //   3596: aload_0
    //   3597: getfield 21	org/bouncycastle2/crypto/digests/RIPEMD160Digest:X	[I
    //   3600: iconst_5
    //   3601: iaload
    //   3602: iadd
    //   3603: iadd
    //   3604: bipush 7
    //   3606: invokespecial 74	org/bouncycastle2/crypto/digests/RIPEMD160Digest:RL	(II)I
    //   3609: iadd
    //   3610: istore 168
    //   3612: aload_0
    //   3613: iload 132
    //   3615: bipush 10
    //   3617: invokespecial 74	org/bouncycastle2/crypto/digests/RIPEMD160Digest:RL	(II)I
    //   3620: istore 169
    //   3622: iload 167
    //   3624: aload_0
    //   3625: ldc 87
    //   3627: iload 133
    //   3629: aload_0
    //   3630: iload 168
    //   3632: iload 166
    //   3634: iload 169
    //   3636: invokespecial 86	org/bouncycastle2/crypto/digests/RIPEMD160Digest:f3	(III)I
    //   3639: iadd
    //   3640: aload_0
    //   3641: getfield 21	org/bouncycastle2/crypto/digests/RIPEMD160Digest:X	[I
    //   3644: iconst_1
    //   3645: iaload
    //   3646: iadd
    //   3647: iadd
    //   3648: bipush 15
    //   3650: invokespecial 74	org/bouncycastle2/crypto/digests/RIPEMD160Digest:RL	(II)I
    //   3653: iadd
    //   3654: istore 170
    //   3656: aload_0
    //   3657: iload 166
    //   3659: bipush 10
    //   3661: invokespecial 74	org/bouncycastle2/crypto/digests/RIPEMD160Digest:RL	(II)I
    //   3664: istore 171
    //   3666: iload 169
    //   3668: aload_0
    //   3669: ldc 87
    //   3671: iload 167
    //   3673: aload_0
    //   3674: iload 170
    //   3676: iload 168
    //   3678: iload 171
    //   3680: invokespecial 86	org/bouncycastle2/crypto/digests/RIPEMD160Digest:f3	(III)I
    //   3683: iadd
    //   3684: aload_0
    //   3685: getfield 21	org/bouncycastle2/crypto/digests/RIPEMD160Digest:X	[I
    //   3688: iconst_3
    //   3689: iaload
    //   3690: iadd
    //   3691: iadd
    //   3692: bipush 11
    //   3694: invokespecial 74	org/bouncycastle2/crypto/digests/RIPEMD160Digest:RL	(II)I
    //   3697: iadd
    //   3698: istore 172
    //   3700: aload_0
    //   3701: iload 168
    //   3703: bipush 10
    //   3705: invokespecial 74	org/bouncycastle2/crypto/digests/RIPEMD160Digest:RL	(II)I
    //   3708: istore 173
    //   3710: iload 171
    //   3712: aload_0
    //   3713: ldc 87
    //   3715: iload 169
    //   3717: aload_0
    //   3718: iload 172
    //   3720: iload 170
    //   3722: iload 173
    //   3724: invokespecial 86	org/bouncycastle2/crypto/digests/RIPEMD160Digest:f3	(III)I
    //   3727: iadd
    //   3728: aload_0
    //   3729: getfield 21	org/bouncycastle2/crypto/digests/RIPEMD160Digest:X	[I
    //   3732: bipush 7
    //   3734: iaload
    //   3735: iadd
    //   3736: iadd
    //   3737: bipush 8
    //   3739: invokespecial 74	org/bouncycastle2/crypto/digests/RIPEMD160Digest:RL	(II)I
    //   3742: iadd
    //   3743: istore 174
    //   3745: aload_0
    //   3746: iload 170
    //   3748: bipush 10
    //   3750: invokespecial 74	org/bouncycastle2/crypto/digests/RIPEMD160Digest:RL	(II)I
    //   3753: istore 175
    //   3755: iload 173
    //   3757: aload_0
    //   3758: ldc 87
    //   3760: iload 171
    //   3762: aload_0
    //   3763: iload 174
    //   3765: iload 172
    //   3767: iload 175
    //   3769: invokespecial 86	org/bouncycastle2/crypto/digests/RIPEMD160Digest:f3	(III)I
    //   3772: iadd
    //   3773: aload_0
    //   3774: getfield 21	org/bouncycastle2/crypto/digests/RIPEMD160Digest:X	[I
    //   3777: bipush 14
    //   3779: iaload
    //   3780: iadd
    //   3781: iadd
    //   3782: bipush 6
    //   3784: invokespecial 74	org/bouncycastle2/crypto/digests/RIPEMD160Digest:RL	(II)I
    //   3787: iadd
    //   3788: istore 176
    //   3790: aload_0
    //   3791: iload 172
    //   3793: bipush 10
    //   3795: invokespecial 74	org/bouncycastle2/crypto/digests/RIPEMD160Digest:RL	(II)I
    //   3798: istore 177
    //   3800: iload 175
    //   3802: aload_0
    //   3803: ldc 87
    //   3805: iload 173
    //   3807: aload_0
    //   3808: iload 176
    //   3810: iload 174
    //   3812: iload 177
    //   3814: invokespecial 86	org/bouncycastle2/crypto/digests/RIPEMD160Digest:f3	(III)I
    //   3817: iadd
    //   3818: aload_0
    //   3819: getfield 21	org/bouncycastle2/crypto/digests/RIPEMD160Digest:X	[I
    //   3822: bipush 6
    //   3824: iaload
    //   3825: iadd
    //   3826: iadd
    //   3827: bipush 6
    //   3829: invokespecial 74	org/bouncycastle2/crypto/digests/RIPEMD160Digest:RL	(II)I
    //   3832: iadd
    //   3833: istore 178
    //   3835: aload_0
    //   3836: iload 174
    //   3838: bipush 10
    //   3840: invokespecial 74	org/bouncycastle2/crypto/digests/RIPEMD160Digest:RL	(II)I
    //   3843: istore 179
    //   3845: iload 177
    //   3847: aload_0
    //   3848: ldc 87
    //   3850: iload 175
    //   3852: aload_0
    //   3853: iload 178
    //   3855: iload 176
    //   3857: iload 179
    //   3859: invokespecial 86	org/bouncycastle2/crypto/digests/RIPEMD160Digest:f3	(III)I
    //   3862: iadd
    //   3863: aload_0
    //   3864: getfield 21	org/bouncycastle2/crypto/digests/RIPEMD160Digest:X	[I
    //   3867: bipush 9
    //   3869: iaload
    //   3870: iadd
    //   3871: iadd
    //   3872: bipush 14
    //   3874: invokespecial 74	org/bouncycastle2/crypto/digests/RIPEMD160Digest:RL	(II)I
    //   3877: iadd
    //   3878: istore 180
    //   3880: aload_0
    //   3881: iload 176
    //   3883: bipush 10
    //   3885: invokespecial 74	org/bouncycastle2/crypto/digests/RIPEMD160Digest:RL	(II)I
    //   3888: istore 181
    //   3890: iload 179
    //   3892: aload_0
    //   3893: ldc 87
    //   3895: iload 177
    //   3897: aload_0
    //   3898: iload 180
    //   3900: iload 178
    //   3902: iload 181
    //   3904: invokespecial 86	org/bouncycastle2/crypto/digests/RIPEMD160Digest:f3	(III)I
    //   3907: iadd
    //   3908: aload_0
    //   3909: getfield 21	org/bouncycastle2/crypto/digests/RIPEMD160Digest:X	[I
    //   3912: bipush 11
    //   3914: iaload
    //   3915: iadd
    //   3916: iadd
    //   3917: bipush 12
    //   3919: invokespecial 74	org/bouncycastle2/crypto/digests/RIPEMD160Digest:RL	(II)I
    //   3922: iadd
    //   3923: istore 182
    //   3925: aload_0
    //   3926: iload 178
    //   3928: bipush 10
    //   3930: invokespecial 74	org/bouncycastle2/crypto/digests/RIPEMD160Digest:RL	(II)I
    //   3933: istore 183
    //   3935: iload 181
    //   3937: aload_0
    //   3938: ldc 87
    //   3940: iload 179
    //   3942: aload_0
    //   3943: iload 182
    //   3945: iload 180
    //   3947: iload 183
    //   3949: invokespecial 86	org/bouncycastle2/crypto/digests/RIPEMD160Digest:f3	(III)I
    //   3952: iadd
    //   3953: aload_0
    //   3954: getfield 21	org/bouncycastle2/crypto/digests/RIPEMD160Digest:X	[I
    //   3957: bipush 8
    //   3959: iaload
    //   3960: iadd
    //   3961: iadd
    //   3962: bipush 13
    //   3964: invokespecial 74	org/bouncycastle2/crypto/digests/RIPEMD160Digest:RL	(II)I
    //   3967: iadd
    //   3968: istore 184
    //   3970: aload_0
    //   3971: iload 180
    //   3973: bipush 10
    //   3975: invokespecial 74	org/bouncycastle2/crypto/digests/RIPEMD160Digest:RL	(II)I
    //   3978: istore 185
    //   3980: iload 183
    //   3982: aload_0
    //   3983: ldc 87
    //   3985: iload 181
    //   3987: aload_0
    //   3988: iload 184
    //   3990: iload 182
    //   3992: iload 185
    //   3994: invokespecial 86	org/bouncycastle2/crypto/digests/RIPEMD160Digest:f3	(III)I
    //   3997: iadd
    //   3998: aload_0
    //   3999: getfield 21	org/bouncycastle2/crypto/digests/RIPEMD160Digest:X	[I
    //   4002: bipush 12
    //   4004: iaload
    //   4005: iadd
    //   4006: iadd
    //   4007: iconst_5
    //   4008: invokespecial 74	org/bouncycastle2/crypto/digests/RIPEMD160Digest:RL	(II)I
    //   4011: iadd
    //   4012: istore 186
    //   4014: aload_0
    //   4015: iload 182
    //   4017: bipush 10
    //   4019: invokespecial 74	org/bouncycastle2/crypto/digests/RIPEMD160Digest:RL	(II)I
    //   4022: istore 187
    //   4024: iload 185
    //   4026: aload_0
    //   4027: ldc 87
    //   4029: iload 183
    //   4031: aload_0
    //   4032: iload 186
    //   4034: iload 184
    //   4036: iload 187
    //   4038: invokespecial 86	org/bouncycastle2/crypto/digests/RIPEMD160Digest:f3	(III)I
    //   4041: iadd
    //   4042: aload_0
    //   4043: getfield 21	org/bouncycastle2/crypto/digests/RIPEMD160Digest:X	[I
    //   4046: iconst_2
    //   4047: iaload
    //   4048: iadd
    //   4049: iadd
    //   4050: bipush 14
    //   4052: invokespecial 74	org/bouncycastle2/crypto/digests/RIPEMD160Digest:RL	(II)I
    //   4055: iadd
    //   4056: istore 188
    //   4058: aload_0
    //   4059: iload 184
    //   4061: bipush 10
    //   4063: invokespecial 74	org/bouncycastle2/crypto/digests/RIPEMD160Digest:RL	(II)I
    //   4066: istore 189
    //   4068: iload 187
    //   4070: aload_0
    //   4071: ldc 87
    //   4073: iload 185
    //   4075: aload_0
    //   4076: iload 188
    //   4078: iload 186
    //   4080: iload 189
    //   4082: invokespecial 86	org/bouncycastle2/crypto/digests/RIPEMD160Digest:f3	(III)I
    //   4085: iadd
    //   4086: aload_0
    //   4087: getfield 21	org/bouncycastle2/crypto/digests/RIPEMD160Digest:X	[I
    //   4090: bipush 10
    //   4092: iaload
    //   4093: iadd
    //   4094: iadd
    //   4095: bipush 13
    //   4097: invokespecial 74	org/bouncycastle2/crypto/digests/RIPEMD160Digest:RL	(II)I
    //   4100: iadd
    //   4101: istore 190
    //   4103: aload_0
    //   4104: iload 186
    //   4106: bipush 10
    //   4108: invokespecial 74	org/bouncycastle2/crypto/digests/RIPEMD160Digest:RL	(II)I
    //   4111: istore 191
    //   4113: iload 189
    //   4115: aload_0
    //   4116: ldc 87
    //   4118: iload 187
    //   4120: aload_0
    //   4121: iload 190
    //   4123: iload 188
    //   4125: iload 191
    //   4127: invokespecial 86	org/bouncycastle2/crypto/digests/RIPEMD160Digest:f3	(III)I
    //   4130: iadd
    //   4131: aload_0
    //   4132: getfield 21	org/bouncycastle2/crypto/digests/RIPEMD160Digest:X	[I
    //   4135: iconst_0
    //   4136: iaload
    //   4137: iadd
    //   4138: iadd
    //   4139: bipush 13
    //   4141: invokespecial 74	org/bouncycastle2/crypto/digests/RIPEMD160Digest:RL	(II)I
    //   4144: iadd
    //   4145: istore 192
    //   4147: aload_0
    //   4148: iload 188
    //   4150: bipush 10
    //   4152: invokespecial 74	org/bouncycastle2/crypto/digests/RIPEMD160Digest:RL	(II)I
    //   4155: istore 193
    //   4157: iload 191
    //   4159: aload_0
    //   4160: ldc 87
    //   4162: iload 189
    //   4164: aload_0
    //   4165: iload 192
    //   4167: iload 190
    //   4169: iload 193
    //   4171: invokespecial 86	org/bouncycastle2/crypto/digests/RIPEMD160Digest:f3	(III)I
    //   4174: iadd
    //   4175: aload_0
    //   4176: getfield 21	org/bouncycastle2/crypto/digests/RIPEMD160Digest:X	[I
    //   4179: iconst_4
    //   4180: iaload
    //   4181: iadd
    //   4182: iadd
    //   4183: bipush 7
    //   4185: invokespecial 74	org/bouncycastle2/crypto/digests/RIPEMD160Digest:RL	(II)I
    //   4188: iadd
    //   4189: istore 194
    //   4191: aload_0
    //   4192: iload 190
    //   4194: bipush 10
    //   4196: invokespecial 74	org/bouncycastle2/crypto/digests/RIPEMD160Digest:RL	(II)I
    //   4199: istore 195
    //   4201: iload 193
    //   4203: aload_0
    //   4204: ldc 87
    //   4206: iload 191
    //   4208: aload_0
    //   4209: iload 194
    //   4211: iload 192
    //   4213: iload 195
    //   4215: invokespecial 86	org/bouncycastle2/crypto/digests/RIPEMD160Digest:f3	(III)I
    //   4218: iadd
    //   4219: aload_0
    //   4220: getfield 21	org/bouncycastle2/crypto/digests/RIPEMD160Digest:X	[I
    //   4223: bipush 13
    //   4225: iaload
    //   4226: iadd
    //   4227: iadd
    //   4228: iconst_5
    //   4229: invokespecial 74	org/bouncycastle2/crypto/digests/RIPEMD160Digest:RL	(II)I
    //   4232: iadd
    //   4233: istore 196
    //   4235: aload_0
    //   4236: iload 192
    //   4238: bipush 10
    //   4240: invokespecial 74	org/bouncycastle2/crypto/digests/RIPEMD160Digest:RL	(II)I
    //   4243: istore 197
    //   4245: iload 163
    //   4247: aload_0
    //   4248: ldc 88
    //   4250: iload 161
    //   4252: aload_0
    //   4253: iload 164
    //   4255: iload 162
    //   4257: iload 165
    //   4259: invokespecial 83	org/bouncycastle2/crypto/digests/RIPEMD160Digest:f4	(III)I
    //   4262: iadd
    //   4263: aload_0
    //   4264: getfield 21	org/bouncycastle2/crypto/digests/RIPEMD160Digest:X	[I
    //   4267: iconst_1
    //   4268: iaload
    //   4269: iadd
    //   4270: iadd
    //   4271: bipush 11
    //   4273: invokespecial 74	org/bouncycastle2/crypto/digests/RIPEMD160Digest:RL	(II)I
    //   4276: iadd
    //   4277: istore 198
    //   4279: aload_0
    //   4280: iload 162
    //   4282: bipush 10
    //   4284: invokespecial 74	org/bouncycastle2/crypto/digests/RIPEMD160Digest:RL	(II)I
    //   4287: istore 199
    //   4289: iload 165
    //   4291: aload_0
    //   4292: ldc 88
    //   4294: iload 163
    //   4296: aload_0
    //   4297: iload 198
    //   4299: iload 164
    //   4301: iload 199
    //   4303: invokespecial 83	org/bouncycastle2/crypto/digests/RIPEMD160Digest:f4	(III)I
    //   4306: iadd
    //   4307: aload_0
    //   4308: getfield 21	org/bouncycastle2/crypto/digests/RIPEMD160Digest:X	[I
    //   4311: bipush 9
    //   4313: iaload
    //   4314: iadd
    //   4315: iadd
    //   4316: bipush 12
    //   4318: invokespecial 74	org/bouncycastle2/crypto/digests/RIPEMD160Digest:RL	(II)I
    //   4321: iadd
    //   4322: istore 200
    //   4324: aload_0
    //   4325: iload 164
    //   4327: bipush 10
    //   4329: invokespecial 74	org/bouncycastle2/crypto/digests/RIPEMD160Digest:RL	(II)I
    //   4332: istore 201
    //   4334: iload 199
    //   4336: aload_0
    //   4337: ldc 88
    //   4339: iload 165
    //   4341: aload_0
    //   4342: iload 200
    //   4344: iload 198
    //   4346: iload 201
    //   4348: invokespecial 83	org/bouncycastle2/crypto/digests/RIPEMD160Digest:f4	(III)I
    //   4351: iadd
    //   4352: aload_0
    //   4353: getfield 21	org/bouncycastle2/crypto/digests/RIPEMD160Digest:X	[I
    //   4356: bipush 11
    //   4358: iaload
    //   4359: iadd
    //   4360: iadd
    //   4361: bipush 14
    //   4363: invokespecial 74	org/bouncycastle2/crypto/digests/RIPEMD160Digest:RL	(II)I
    //   4366: iadd
    //   4367: istore 202
    //   4369: aload_0
    //   4370: iload 198
    //   4372: bipush 10
    //   4374: invokespecial 74	org/bouncycastle2/crypto/digests/RIPEMD160Digest:RL	(II)I
    //   4377: istore 203
    //   4379: iload 201
    //   4381: aload_0
    //   4382: ldc 88
    //   4384: iload 199
    //   4386: aload_0
    //   4387: iload 202
    //   4389: iload 200
    //   4391: iload 203
    //   4393: invokespecial 83	org/bouncycastle2/crypto/digests/RIPEMD160Digest:f4	(III)I
    //   4396: iadd
    //   4397: aload_0
    //   4398: getfield 21	org/bouncycastle2/crypto/digests/RIPEMD160Digest:X	[I
    //   4401: bipush 10
    //   4403: iaload
    //   4404: iadd
    //   4405: iadd
    //   4406: bipush 15
    //   4408: invokespecial 74	org/bouncycastle2/crypto/digests/RIPEMD160Digest:RL	(II)I
    //   4411: iadd
    //   4412: istore 204
    //   4414: aload_0
    //   4415: iload 200
    //   4417: bipush 10
    //   4419: invokespecial 74	org/bouncycastle2/crypto/digests/RIPEMD160Digest:RL	(II)I
    //   4422: istore 205
    //   4424: iload 203
    //   4426: aload_0
    //   4427: ldc 88
    //   4429: iload 201
    //   4431: aload_0
    //   4432: iload 204
    //   4434: iload 202
    //   4436: iload 205
    //   4438: invokespecial 83	org/bouncycastle2/crypto/digests/RIPEMD160Digest:f4	(III)I
    //   4441: iadd
    //   4442: aload_0
    //   4443: getfield 21	org/bouncycastle2/crypto/digests/RIPEMD160Digest:X	[I
    //   4446: iconst_0
    //   4447: iaload
    //   4448: iadd
    //   4449: iadd
    //   4450: bipush 14
    //   4452: invokespecial 74	org/bouncycastle2/crypto/digests/RIPEMD160Digest:RL	(II)I
    //   4455: iadd
    //   4456: istore 206
    //   4458: aload_0
    //   4459: iload 202
    //   4461: bipush 10
    //   4463: invokespecial 74	org/bouncycastle2/crypto/digests/RIPEMD160Digest:RL	(II)I
    //   4466: istore 207
    //   4468: iload 205
    //   4470: aload_0
    //   4471: ldc 88
    //   4473: iload 203
    //   4475: aload_0
    //   4476: iload 206
    //   4478: iload 204
    //   4480: iload 207
    //   4482: invokespecial 83	org/bouncycastle2/crypto/digests/RIPEMD160Digest:f4	(III)I
    //   4485: iadd
    //   4486: aload_0
    //   4487: getfield 21	org/bouncycastle2/crypto/digests/RIPEMD160Digest:X	[I
    //   4490: bipush 8
    //   4492: iaload
    //   4493: iadd
    //   4494: iadd
    //   4495: bipush 15
    //   4497: invokespecial 74	org/bouncycastle2/crypto/digests/RIPEMD160Digest:RL	(II)I
    //   4500: iadd
    //   4501: istore 208
    //   4503: aload_0
    //   4504: iload 204
    //   4506: bipush 10
    //   4508: invokespecial 74	org/bouncycastle2/crypto/digests/RIPEMD160Digest:RL	(II)I
    //   4511: istore 209
    //   4513: iload 207
    //   4515: aload_0
    //   4516: ldc 88
    //   4518: iload 205
    //   4520: aload_0
    //   4521: iload 208
    //   4523: iload 206
    //   4525: iload 209
    //   4527: invokespecial 83	org/bouncycastle2/crypto/digests/RIPEMD160Digest:f4	(III)I
    //   4530: iadd
    //   4531: aload_0
    //   4532: getfield 21	org/bouncycastle2/crypto/digests/RIPEMD160Digest:X	[I
    //   4535: bipush 12
    //   4537: iaload
    //   4538: iadd
    //   4539: iadd
    //   4540: bipush 9
    //   4542: invokespecial 74	org/bouncycastle2/crypto/digests/RIPEMD160Digest:RL	(II)I
    //   4545: iadd
    //   4546: istore 210
    //   4548: aload_0
    //   4549: iload 206
    //   4551: bipush 10
    //   4553: invokespecial 74	org/bouncycastle2/crypto/digests/RIPEMD160Digest:RL	(II)I
    //   4556: istore 211
    //   4558: iload 209
    //   4560: aload_0
    //   4561: ldc 88
    //   4563: iload 207
    //   4565: aload_0
    //   4566: iload 210
    //   4568: iload 208
    //   4570: iload 211
    //   4572: invokespecial 83	org/bouncycastle2/crypto/digests/RIPEMD160Digest:f4	(III)I
    //   4575: iadd
    //   4576: aload_0
    //   4577: getfield 21	org/bouncycastle2/crypto/digests/RIPEMD160Digest:X	[I
    //   4580: iconst_4
    //   4581: iaload
    //   4582: iadd
    //   4583: iadd
    //   4584: bipush 8
    //   4586: invokespecial 74	org/bouncycastle2/crypto/digests/RIPEMD160Digest:RL	(II)I
    //   4589: iadd
    //   4590: istore 212
    //   4592: aload_0
    //   4593: iload 208
    //   4595: bipush 10
    //   4597: invokespecial 74	org/bouncycastle2/crypto/digests/RIPEMD160Digest:RL	(II)I
    //   4600: istore 213
    //   4602: iload 211
    //   4604: aload_0
    //   4605: ldc 88
    //   4607: iload 209
    //   4609: aload_0
    //   4610: iload 212
    //   4612: iload 210
    //   4614: iload 213
    //   4616: invokespecial 83	org/bouncycastle2/crypto/digests/RIPEMD160Digest:f4	(III)I
    //   4619: iadd
    //   4620: aload_0
    //   4621: getfield 21	org/bouncycastle2/crypto/digests/RIPEMD160Digest:X	[I
    //   4624: bipush 13
    //   4626: iaload
    //   4627: iadd
    //   4628: iadd
    //   4629: bipush 9
    //   4631: invokespecial 74	org/bouncycastle2/crypto/digests/RIPEMD160Digest:RL	(II)I
    //   4634: iadd
    //   4635: istore 214
    //   4637: aload_0
    //   4638: iload 210
    //   4640: bipush 10
    //   4642: invokespecial 74	org/bouncycastle2/crypto/digests/RIPEMD160Digest:RL	(II)I
    //   4645: istore 215
    //   4647: iload 213
    //   4649: aload_0
    //   4650: ldc 88
    //   4652: iload 211
    //   4654: aload_0
    //   4655: iload 214
    //   4657: iload 212
    //   4659: iload 215
    //   4661: invokespecial 83	org/bouncycastle2/crypto/digests/RIPEMD160Digest:f4	(III)I
    //   4664: iadd
    //   4665: aload_0
    //   4666: getfield 21	org/bouncycastle2/crypto/digests/RIPEMD160Digest:X	[I
    //   4669: iconst_3
    //   4670: iaload
    //   4671: iadd
    //   4672: iadd
    //   4673: bipush 14
    //   4675: invokespecial 74	org/bouncycastle2/crypto/digests/RIPEMD160Digest:RL	(II)I
    //   4678: iadd
    //   4679: istore 216
    //   4681: aload_0
    //   4682: iload 212
    //   4684: bipush 10
    //   4686: invokespecial 74	org/bouncycastle2/crypto/digests/RIPEMD160Digest:RL	(II)I
    //   4689: istore 217
    //   4691: iload 215
    //   4693: aload_0
    //   4694: ldc 88
    //   4696: iload 213
    //   4698: aload_0
    //   4699: iload 216
    //   4701: iload 214
    //   4703: iload 217
    //   4705: invokespecial 83	org/bouncycastle2/crypto/digests/RIPEMD160Digest:f4	(III)I
    //   4708: iadd
    //   4709: aload_0
    //   4710: getfield 21	org/bouncycastle2/crypto/digests/RIPEMD160Digest:X	[I
    //   4713: bipush 7
    //   4715: iaload
    //   4716: iadd
    //   4717: iadd
    //   4718: iconst_5
    //   4719: invokespecial 74	org/bouncycastle2/crypto/digests/RIPEMD160Digest:RL	(II)I
    //   4722: iadd
    //   4723: istore 218
    //   4725: aload_0
    //   4726: iload 214
    //   4728: bipush 10
    //   4730: invokespecial 74	org/bouncycastle2/crypto/digests/RIPEMD160Digest:RL	(II)I
    //   4733: istore 219
    //   4735: iload 217
    //   4737: aload_0
    //   4738: ldc 88
    //   4740: iload 215
    //   4742: aload_0
    //   4743: iload 218
    //   4745: iload 216
    //   4747: iload 219
    //   4749: invokespecial 83	org/bouncycastle2/crypto/digests/RIPEMD160Digest:f4	(III)I
    //   4752: iadd
    //   4753: aload_0
    //   4754: getfield 21	org/bouncycastle2/crypto/digests/RIPEMD160Digest:X	[I
    //   4757: bipush 15
    //   4759: iaload
    //   4760: iadd
    //   4761: iadd
    //   4762: bipush 6
    //   4764: invokespecial 74	org/bouncycastle2/crypto/digests/RIPEMD160Digest:RL	(II)I
    //   4767: iadd
    //   4768: istore 220
    //   4770: aload_0
    //   4771: iload 216
    //   4773: bipush 10
    //   4775: invokespecial 74	org/bouncycastle2/crypto/digests/RIPEMD160Digest:RL	(II)I
    //   4778: istore 221
    //   4780: iload 219
    //   4782: aload_0
    //   4783: ldc 88
    //   4785: iload 217
    //   4787: aload_0
    //   4788: iload 220
    //   4790: iload 218
    //   4792: iload 221
    //   4794: invokespecial 83	org/bouncycastle2/crypto/digests/RIPEMD160Digest:f4	(III)I
    //   4797: iadd
    //   4798: aload_0
    //   4799: getfield 21	org/bouncycastle2/crypto/digests/RIPEMD160Digest:X	[I
    //   4802: bipush 14
    //   4804: iaload
    //   4805: iadd
    //   4806: iadd
    //   4807: bipush 8
    //   4809: invokespecial 74	org/bouncycastle2/crypto/digests/RIPEMD160Digest:RL	(II)I
    //   4812: iadd
    //   4813: istore 222
    //   4815: aload_0
    //   4816: iload 218
    //   4818: bipush 10
    //   4820: invokespecial 74	org/bouncycastle2/crypto/digests/RIPEMD160Digest:RL	(II)I
    //   4823: istore 223
    //   4825: iload 221
    //   4827: aload_0
    //   4828: ldc 88
    //   4830: iload 219
    //   4832: aload_0
    //   4833: iload 222
    //   4835: iload 220
    //   4837: iload 223
    //   4839: invokespecial 83	org/bouncycastle2/crypto/digests/RIPEMD160Digest:f4	(III)I
    //   4842: iadd
    //   4843: aload_0
    //   4844: getfield 21	org/bouncycastle2/crypto/digests/RIPEMD160Digest:X	[I
    //   4847: iconst_5
    //   4848: iaload
    //   4849: iadd
    //   4850: iadd
    //   4851: bipush 6
    //   4853: invokespecial 74	org/bouncycastle2/crypto/digests/RIPEMD160Digest:RL	(II)I
    //   4856: iadd
    //   4857: istore 224
    //   4859: aload_0
    //   4860: iload 220
    //   4862: bipush 10
    //   4864: invokespecial 74	org/bouncycastle2/crypto/digests/RIPEMD160Digest:RL	(II)I
    //   4867: istore 225
    //   4869: iload 223
    //   4871: aload_0
    //   4872: ldc 88
    //   4874: iload 221
    //   4876: aload_0
    //   4877: iload 224
    //   4879: iload 222
    //   4881: iload 225
    //   4883: invokespecial 83	org/bouncycastle2/crypto/digests/RIPEMD160Digest:f4	(III)I
    //   4886: iadd
    //   4887: aload_0
    //   4888: getfield 21	org/bouncycastle2/crypto/digests/RIPEMD160Digest:X	[I
    //   4891: bipush 6
    //   4893: iaload
    //   4894: iadd
    //   4895: iadd
    //   4896: iconst_5
    //   4897: invokespecial 74	org/bouncycastle2/crypto/digests/RIPEMD160Digest:RL	(II)I
    //   4900: iadd
    //   4901: istore 226
    //   4903: aload_0
    //   4904: iload 222
    //   4906: bipush 10
    //   4908: invokespecial 74	org/bouncycastle2/crypto/digests/RIPEMD160Digest:RL	(II)I
    //   4911: istore 227
    //   4913: iload 225
    //   4915: aload_0
    //   4916: ldc 88
    //   4918: iload 223
    //   4920: aload_0
    //   4921: iload 226
    //   4923: iload 224
    //   4925: iload 227
    //   4927: invokespecial 83	org/bouncycastle2/crypto/digests/RIPEMD160Digest:f4	(III)I
    //   4930: iadd
    //   4931: aload_0
    //   4932: getfield 21	org/bouncycastle2/crypto/digests/RIPEMD160Digest:X	[I
    //   4935: iconst_2
    //   4936: iaload
    //   4937: iadd
    //   4938: iadd
    //   4939: bipush 12
    //   4941: invokespecial 74	org/bouncycastle2/crypto/digests/RIPEMD160Digest:RL	(II)I
    //   4944: iadd
    //   4945: istore 228
    //   4947: aload_0
    //   4948: iload 224
    //   4950: bipush 10
    //   4952: invokespecial 74	org/bouncycastle2/crypto/digests/RIPEMD160Digest:RL	(II)I
    //   4955: istore 229
    //   4957: iload 195
    //   4959: aload_0
    //   4960: ldc 89
    //   4962: iload 193
    //   4964: aload_0
    //   4965: iload 196
    //   4967: iload 194
    //   4969: iload 197
    //   4971: invokespecial 80	org/bouncycastle2/crypto/digests/RIPEMD160Digest:f2	(III)I
    //   4974: iadd
    //   4975: aload_0
    //   4976: getfield 21	org/bouncycastle2/crypto/digests/RIPEMD160Digest:X	[I
    //   4979: bipush 8
    //   4981: iaload
    //   4982: iadd
    //   4983: iadd
    //   4984: bipush 15
    //   4986: invokespecial 74	org/bouncycastle2/crypto/digests/RIPEMD160Digest:RL	(II)I
    //   4989: iadd
    //   4990: istore 230
    //   4992: aload_0
    //   4993: iload 194
    //   4995: bipush 10
    //   4997: invokespecial 74	org/bouncycastle2/crypto/digests/RIPEMD160Digest:RL	(II)I
    //   5000: istore 231
    //   5002: iload 197
    //   5004: aload_0
    //   5005: ldc 89
    //   5007: iload 195
    //   5009: aload_0
    //   5010: iload 230
    //   5012: iload 196
    //   5014: iload 231
    //   5016: invokespecial 80	org/bouncycastle2/crypto/digests/RIPEMD160Digest:f2	(III)I
    //   5019: iadd
    //   5020: aload_0
    //   5021: getfield 21	org/bouncycastle2/crypto/digests/RIPEMD160Digest:X	[I
    //   5024: bipush 6
    //   5026: iaload
    //   5027: iadd
    //   5028: iadd
    //   5029: iconst_5
    //   5030: invokespecial 74	org/bouncycastle2/crypto/digests/RIPEMD160Digest:RL	(II)I
    //   5033: iadd
    //   5034: istore 232
    //   5036: aload_0
    //   5037: iload 196
    //   5039: bipush 10
    //   5041: invokespecial 74	org/bouncycastle2/crypto/digests/RIPEMD160Digest:RL	(II)I
    //   5044: istore 233
    //   5046: iload 231
    //   5048: aload_0
    //   5049: ldc 89
    //   5051: iload 197
    //   5053: aload_0
    //   5054: iload 232
    //   5056: iload 230
    //   5058: iload 233
    //   5060: invokespecial 80	org/bouncycastle2/crypto/digests/RIPEMD160Digest:f2	(III)I
    //   5063: iadd
    //   5064: aload_0
    //   5065: getfield 21	org/bouncycastle2/crypto/digests/RIPEMD160Digest:X	[I
    //   5068: iconst_4
    //   5069: iaload
    //   5070: iadd
    //   5071: iadd
    //   5072: bipush 8
    //   5074: invokespecial 74	org/bouncycastle2/crypto/digests/RIPEMD160Digest:RL	(II)I
    //   5077: iadd
    //   5078: istore 234
    //   5080: aload_0
    //   5081: iload 230
    //   5083: bipush 10
    //   5085: invokespecial 74	org/bouncycastle2/crypto/digests/RIPEMD160Digest:RL	(II)I
    //   5088: istore 235
    //   5090: iload 233
    //   5092: aload_0
    //   5093: ldc 89
    //   5095: iload 231
    //   5097: aload_0
    //   5098: iload 234
    //   5100: iload 232
    //   5102: iload 235
    //   5104: invokespecial 80	org/bouncycastle2/crypto/digests/RIPEMD160Digest:f2	(III)I
    //   5107: iadd
    //   5108: aload_0
    //   5109: getfield 21	org/bouncycastle2/crypto/digests/RIPEMD160Digest:X	[I
    //   5112: iconst_1
    //   5113: iaload
    //   5114: iadd
    //   5115: iadd
    //   5116: bipush 11
    //   5118: invokespecial 74	org/bouncycastle2/crypto/digests/RIPEMD160Digest:RL	(II)I
    //   5121: iadd
    //   5122: istore 236
    //   5124: aload_0
    //   5125: iload 232
    //   5127: bipush 10
    //   5129: invokespecial 74	org/bouncycastle2/crypto/digests/RIPEMD160Digest:RL	(II)I
    //   5132: istore 237
    //   5134: iload 235
    //   5136: aload_0
    //   5137: ldc 89
    //   5139: iload 233
    //   5141: aload_0
    //   5142: iload 236
    //   5144: iload 234
    //   5146: iload 237
    //   5148: invokespecial 80	org/bouncycastle2/crypto/digests/RIPEMD160Digest:f2	(III)I
    //   5151: iadd
    //   5152: aload_0
    //   5153: getfield 21	org/bouncycastle2/crypto/digests/RIPEMD160Digest:X	[I
    //   5156: iconst_3
    //   5157: iaload
    //   5158: iadd
    //   5159: iadd
    //   5160: bipush 14
    //   5162: invokespecial 74	org/bouncycastle2/crypto/digests/RIPEMD160Digest:RL	(II)I
    //   5165: iadd
    //   5166: istore 238
    //   5168: aload_0
    //   5169: iload 234
    //   5171: bipush 10
    //   5173: invokespecial 74	org/bouncycastle2/crypto/digests/RIPEMD160Digest:RL	(II)I
    //   5176: istore 239
    //   5178: iload 237
    //   5180: aload_0
    //   5181: ldc 89
    //   5183: iload 235
    //   5185: aload_0
    //   5186: iload 238
    //   5188: iload 236
    //   5190: iload 239
    //   5192: invokespecial 80	org/bouncycastle2/crypto/digests/RIPEMD160Digest:f2	(III)I
    //   5195: iadd
    //   5196: aload_0
    //   5197: getfield 21	org/bouncycastle2/crypto/digests/RIPEMD160Digest:X	[I
    //   5200: bipush 11
    //   5202: iaload
    //   5203: iadd
    //   5204: iadd
    //   5205: bipush 14
    //   5207: invokespecial 74	org/bouncycastle2/crypto/digests/RIPEMD160Digest:RL	(II)I
    //   5210: iadd
    //   5211: istore 240
    //   5213: aload_0
    //   5214: iload 236
    //   5216: bipush 10
    //   5218: invokespecial 74	org/bouncycastle2/crypto/digests/RIPEMD160Digest:RL	(II)I
    //   5221: istore 241
    //   5223: iload 239
    //   5225: aload_0
    //   5226: ldc 89
    //   5228: iload 237
    //   5230: aload_0
    //   5231: iload 240
    //   5233: iload 238
    //   5235: iload 241
    //   5237: invokespecial 80	org/bouncycastle2/crypto/digests/RIPEMD160Digest:f2	(III)I
    //   5240: iadd
    //   5241: aload_0
    //   5242: getfield 21	org/bouncycastle2/crypto/digests/RIPEMD160Digest:X	[I
    //   5245: bipush 15
    //   5247: iaload
    //   5248: iadd
    //   5249: iadd
    //   5250: bipush 6
    //   5252: invokespecial 74	org/bouncycastle2/crypto/digests/RIPEMD160Digest:RL	(II)I
    //   5255: iadd
    //   5256: istore 242
    //   5258: aload_0
    //   5259: iload 238
    //   5261: bipush 10
    //   5263: invokespecial 74	org/bouncycastle2/crypto/digests/RIPEMD160Digest:RL	(II)I
    //   5266: istore 243
    //   5268: iload 241
    //   5270: aload_0
    //   5271: ldc 89
    //   5273: iload 239
    //   5275: aload_0
    //   5276: iload 242
    //   5278: iload 240
    //   5280: iload 243
    //   5282: invokespecial 80	org/bouncycastle2/crypto/digests/RIPEMD160Digest:f2	(III)I
    //   5285: iadd
    //   5286: aload_0
    //   5287: getfield 21	org/bouncycastle2/crypto/digests/RIPEMD160Digest:X	[I
    //   5290: iconst_0
    //   5291: iaload
    //   5292: iadd
    //   5293: iadd
    //   5294: bipush 14
    //   5296: invokespecial 74	org/bouncycastle2/crypto/digests/RIPEMD160Digest:RL	(II)I
    //   5299: iadd
    //   5300: istore 244
    //   5302: aload_0
    //   5303: iload 240
    //   5305: bipush 10
    //   5307: invokespecial 74	org/bouncycastle2/crypto/digests/RIPEMD160Digest:RL	(II)I
    //   5310: istore 245
    //   5312: iload 243
    //   5314: aload_0
    //   5315: ldc 89
    //   5317: iload 241
    //   5319: aload_0
    //   5320: iload 244
    //   5322: iload 242
    //   5324: iload 245
    //   5326: invokespecial 80	org/bouncycastle2/crypto/digests/RIPEMD160Digest:f2	(III)I
    //   5329: iadd
    //   5330: aload_0
    //   5331: getfield 21	org/bouncycastle2/crypto/digests/RIPEMD160Digest:X	[I
    //   5334: iconst_5
    //   5335: iaload
    //   5336: iadd
    //   5337: iadd
    //   5338: bipush 6
    //   5340: invokespecial 74	org/bouncycastle2/crypto/digests/RIPEMD160Digest:RL	(II)I
    //   5343: iadd
    //   5344: istore 246
    //   5346: aload_0
    //   5347: iload 242
    //   5349: bipush 10
    //   5351: invokespecial 74	org/bouncycastle2/crypto/digests/RIPEMD160Digest:RL	(II)I
    //   5354: istore 247
    //   5356: iload 245
    //   5358: aload_0
    //   5359: ldc 89
    //   5361: iload 243
    //   5363: aload_0
    //   5364: iload 246
    //   5366: iload 244
    //   5368: iload 247
    //   5370: invokespecial 80	org/bouncycastle2/crypto/digests/RIPEMD160Digest:f2	(III)I
    //   5373: iadd
    //   5374: aload_0
    //   5375: getfield 21	org/bouncycastle2/crypto/digests/RIPEMD160Digest:X	[I
    //   5378: bipush 12
    //   5380: iaload
    //   5381: iadd
    //   5382: iadd
    //   5383: bipush 9
    //   5385: invokespecial 74	org/bouncycastle2/crypto/digests/RIPEMD160Digest:RL	(II)I
    //   5388: iadd
    //   5389: istore 248
    //   5391: aload_0
    //   5392: iload 244
    //   5394: bipush 10
    //   5396: invokespecial 74	org/bouncycastle2/crypto/digests/RIPEMD160Digest:RL	(II)I
    //   5399: istore 249
    //   5401: iload 247
    //   5403: aload_0
    //   5404: ldc 89
    //   5406: iload 245
    //   5408: aload_0
    //   5409: iload 248
    //   5411: iload 246
    //   5413: iload 249
    //   5415: invokespecial 80	org/bouncycastle2/crypto/digests/RIPEMD160Digest:f2	(III)I
    //   5418: iadd
    //   5419: aload_0
    //   5420: getfield 21	org/bouncycastle2/crypto/digests/RIPEMD160Digest:X	[I
    //   5423: iconst_2
    //   5424: iaload
    //   5425: iadd
    //   5426: iadd
    //   5427: bipush 12
    //   5429: invokespecial 74	org/bouncycastle2/crypto/digests/RIPEMD160Digest:RL	(II)I
    //   5432: iadd
    //   5433: istore 250
    //   5435: aload_0
    //   5436: iload 246
    //   5438: bipush 10
    //   5440: invokespecial 74	org/bouncycastle2/crypto/digests/RIPEMD160Digest:RL	(II)I
    //   5443: istore 251
    //   5445: iload 249
    //   5447: aload_0
    //   5448: ldc 89
    //   5450: iload 247
    //   5452: aload_0
    //   5453: iload 250
    //   5455: iload 248
    //   5457: iload 251
    //   5459: invokespecial 80	org/bouncycastle2/crypto/digests/RIPEMD160Digest:f2	(III)I
    //   5462: iadd
    //   5463: aload_0
    //   5464: getfield 21	org/bouncycastle2/crypto/digests/RIPEMD160Digest:X	[I
    //   5467: bipush 13
    //   5469: iaload
    //   5470: iadd
    //   5471: iadd
    //   5472: bipush 9
    //   5474: invokespecial 74	org/bouncycastle2/crypto/digests/RIPEMD160Digest:RL	(II)I
    //   5477: iadd
    //   5478: istore 252
    //   5480: aload_0
    //   5481: iload 248
    //   5483: bipush 10
    //   5485: invokespecial 74	org/bouncycastle2/crypto/digests/RIPEMD160Digest:RL	(II)I
    //   5488: istore 253
    //   5490: iload 251
    //   5492: aload_0
    //   5493: ldc 89
    //   5495: iload 249
    //   5497: aload_0
    //   5498: iload 252
    //   5500: iload 250
    //   5502: iload 253
    //   5504: invokespecial 80	org/bouncycastle2/crypto/digests/RIPEMD160Digest:f2	(III)I
    //   5507: iadd
    //   5508: aload_0
    //   5509: getfield 21	org/bouncycastle2/crypto/digests/RIPEMD160Digest:X	[I
    //   5512: bipush 9
    //   5514: iaload
    //   5515: iadd
    //   5516: iadd
    //   5517: bipush 12
    //   5519: invokespecial 74	org/bouncycastle2/crypto/digests/RIPEMD160Digest:RL	(II)I
    //   5522: iadd
    //   5523: istore 254
    //   5525: aload_0
    //   5526: iload 250
    //   5528: bipush 10
    //   5530: invokespecial 74	org/bouncycastle2/crypto/digests/RIPEMD160Digest:RL	(II)I
    //   5533: istore 255
    //   5535: iload 253
    //   5537: aload_0
    //   5538: ldc 89
    //   5540: iload 251
    //   5542: aload_0
    //   5543: iload 254
    //   5545: iload 252
    //   5547: iload 255
    //   5549: invokespecial 80	org/bouncycastle2/crypto/digests/RIPEMD160Digest:f2	(III)I
    //   5552: iadd
    //   5553: aload_0
    //   5554: getfield 21	org/bouncycastle2/crypto/digests/RIPEMD160Digest:X	[I
    //   5557: bipush 7
    //   5559: iaload
    //   5560: iadd
    //   5561: iadd
    //   5562: iconst_5
    //   5563: invokespecial 74	org/bouncycastle2/crypto/digests/RIPEMD160Digest:RL	(II)I
    //   5566: iadd
    //   5567: wide
    //   5571: aload_0
    //   5572: iload 252
    //   5574: bipush 10
    //   5576: invokespecial 74	org/bouncycastle2/crypto/digests/RIPEMD160Digest:RL	(II)I
    //   5579: wide
    //   5583: iload 255
    //   5585: aload_0
    //   5586: ldc 89
    //   5588: iload 253
    //   5590: aload_0
    //   5591: wide
    //   5595: iload 254
    //   5597: wide
    //   5601: invokespecial 80	org/bouncycastle2/crypto/digests/RIPEMD160Digest:f2	(III)I
    //   5604: iadd
    //   5605: aload_0
    //   5606: getfield 21	org/bouncycastle2/crypto/digests/RIPEMD160Digest:X	[I
    //   5609: bipush 10
    //   5611: iaload
    //   5612: iadd
    //   5613: iadd
    //   5614: bipush 15
    //   5616: invokespecial 74	org/bouncycastle2/crypto/digests/RIPEMD160Digest:RL	(II)I
    //   5619: iadd
    //   5620: wide
    //   5624: aload_0
    //   5625: iload 254
    //   5627: bipush 10
    //   5629: invokespecial 74	org/bouncycastle2/crypto/digests/RIPEMD160Digest:RL	(II)I
    //   5632: wide
    //   5636: wide
    //   5640: aload_0
    //   5641: ldc 89
    //   5643: iload 255
    //   5645: aload_0
    //   5646: wide
    //   5650: wide
    //   5654: wide
    //   5658: invokespecial 80	org/bouncycastle2/crypto/digests/RIPEMD160Digest:f2	(III)I
    //   5661: iadd
    //   5662: aload_0
    //   5663: getfield 21	org/bouncycastle2/crypto/digests/RIPEMD160Digest:X	[I
    //   5666: bipush 14
    //   5668: iaload
    //   5669: iadd
    //   5670: iadd
    //   5671: bipush 8
    //   5673: invokespecial 74	org/bouncycastle2/crypto/digests/RIPEMD160Digest:RL	(II)I
    //   5676: iadd
    //   5677: wide
    //   5681: aload_0
    //   5682: wide
    //   5686: bipush 10
    //   5688: invokespecial 74	org/bouncycastle2/crypto/digests/RIPEMD160Digest:RL	(II)I
    //   5691: wide
    //   5695: iload 227
    //   5697: aload_0
    //   5698: ldc 90
    //   5700: iload 225
    //   5702: aload_0
    //   5703: iload 228
    //   5705: iload 226
    //   5707: iload 229
    //   5709: invokespecial 77	org/bouncycastle2/crypto/digests/RIPEMD160Digest:f5	(III)I
    //   5712: iadd
    //   5713: aload_0
    //   5714: getfield 21	org/bouncycastle2/crypto/digests/RIPEMD160Digest:X	[I
    //   5717: iconst_4
    //   5718: iaload
    //   5719: iadd
    //   5720: iadd
    //   5721: bipush 9
    //   5723: invokespecial 74	org/bouncycastle2/crypto/digests/RIPEMD160Digest:RL	(II)I
    //   5726: iadd
    //   5727: wide
    //   5731: aload_0
    //   5732: iload 226
    //   5734: bipush 10
    //   5736: invokespecial 74	org/bouncycastle2/crypto/digests/RIPEMD160Digest:RL	(II)I
    //   5739: wide
    //   5743: iload 229
    //   5745: aload_0
    //   5746: ldc 90
    //   5748: iload 227
    //   5750: aload_0
    //   5751: wide
    //   5755: iload 228
    //   5757: wide
    //   5761: invokespecial 77	org/bouncycastle2/crypto/digests/RIPEMD160Digest:f5	(III)I
    //   5764: iadd
    //   5765: aload_0
    //   5766: getfield 21	org/bouncycastle2/crypto/digests/RIPEMD160Digest:X	[I
    //   5769: iconst_0
    //   5770: iaload
    //   5771: iadd
    //   5772: iadd
    //   5773: bipush 15
    //   5775: invokespecial 74	org/bouncycastle2/crypto/digests/RIPEMD160Digest:RL	(II)I
    //   5778: iadd
    //   5779: wide
    //   5783: aload_0
    //   5784: iload 228
    //   5786: bipush 10
    //   5788: invokespecial 74	org/bouncycastle2/crypto/digests/RIPEMD160Digest:RL	(II)I
    //   5791: wide
    //   5795: wide
    //   5799: aload_0
    //   5800: ldc 90
    //   5802: iload 229
    //   5804: aload_0
    //   5805: wide
    //   5809: wide
    //   5813: wide
    //   5817: invokespecial 77	org/bouncycastle2/crypto/digests/RIPEMD160Digest:f5	(III)I
    //   5820: iadd
    //   5821: aload_0
    //   5822: getfield 21	org/bouncycastle2/crypto/digests/RIPEMD160Digest:X	[I
    //   5825: iconst_5
    //   5826: iaload
    //   5827: iadd
    //   5828: iadd
    //   5829: iconst_5
    //   5830: invokespecial 74	org/bouncycastle2/crypto/digests/RIPEMD160Digest:RL	(II)I
    //   5833: iadd
    //   5834: wide
    //   5838: aload_0
    //   5839: wide
    //   5843: bipush 10
    //   5845: invokespecial 74	org/bouncycastle2/crypto/digests/RIPEMD160Digest:RL	(II)I
    //   5848: wide
    //   5852: wide
    //   5856: aload_0
    //   5857: ldc 90
    //   5859: wide
    //   5863: aload_0
    //   5864: wide
    //   5868: wide
    //   5872: wide
    //   5876: invokespecial 77	org/bouncycastle2/crypto/digests/RIPEMD160Digest:f5	(III)I
    //   5879: iadd
    //   5880: aload_0
    //   5881: getfield 21	org/bouncycastle2/crypto/digests/RIPEMD160Digest:X	[I
    //   5884: bipush 9
    //   5886: iaload
    //   5887: iadd
    //   5888: iadd
    //   5889: bipush 11
    //   5891: invokespecial 74	org/bouncycastle2/crypto/digests/RIPEMD160Digest:RL	(II)I
    //   5894: iadd
    //   5895: wide
    //   5899: aload_0
    //   5900: wide
    //   5904: bipush 10
    //   5906: invokespecial 74	org/bouncycastle2/crypto/digests/RIPEMD160Digest:RL	(II)I
    //   5909: wide
    //   5913: wide
    //   5917: aload_0
    //   5918: ldc 90
    //   5920: wide
    //   5924: aload_0
    //   5925: wide
    //   5929: wide
    //   5933: wide
    //   5937: invokespecial 77	org/bouncycastle2/crypto/digests/RIPEMD160Digest:f5	(III)I
    //   5940: iadd
    //   5941: aload_0
    //   5942: getfield 21	org/bouncycastle2/crypto/digests/RIPEMD160Digest:X	[I
    //   5945: bipush 7
    //   5947: iaload
    //   5948: iadd
    //   5949: iadd
    //   5950: bipush 6
    //   5952: invokespecial 74	org/bouncycastle2/crypto/digests/RIPEMD160Digest:RL	(II)I
    //   5955: iadd
    //   5956: wide
    //   5960: aload_0
    //   5961: wide
    //   5965: bipush 10
    //   5967: invokespecial 74	org/bouncycastle2/crypto/digests/RIPEMD160Digest:RL	(II)I
    //   5970: wide
    //   5974: wide
    //   5978: aload_0
    //   5979: ldc 90
    //   5981: wide
    //   5985: aload_0
    //   5986: wide
    //   5990: wide
    //   5994: wide
    //   5998: invokespecial 77	org/bouncycastle2/crypto/digests/RIPEMD160Digest:f5	(III)I
    //   6001: iadd
    //   6002: aload_0
    //   6003: getfield 21	org/bouncycastle2/crypto/digests/RIPEMD160Digest:X	[I
    //   6006: bipush 12
    //   6008: iaload
    //   6009: iadd
    //   6010: iadd
    //   6011: bipush 8
    //   6013: invokespecial 74	org/bouncycastle2/crypto/digests/RIPEMD160Digest:RL	(II)I
    //   6016: iadd
    //   6017: wide
    //   6021: aload_0
    //   6022: wide
    //   6026: bipush 10
    //   6028: invokespecial 74	org/bouncycastle2/crypto/digests/RIPEMD160Digest:RL	(II)I
    //   6031: wide
    //   6035: wide
    //   6039: aload_0
    //   6040: ldc 90
    //   6042: wide
    //   6046: aload_0
    //   6047: wide
    //   6051: wide
    //   6055: wide
    //   6059: invokespecial 77	org/bouncycastle2/crypto/digests/RIPEMD160Digest:f5	(III)I
    //   6062: iadd
    //   6063: aload_0
    //   6064: getfield 21	org/bouncycastle2/crypto/digests/RIPEMD160Digest:X	[I
    //   6067: iconst_2
    //   6068: iaload
    //   6069: iadd
    //   6070: iadd
    //   6071: bipush 13
    //   6073: invokespecial 74	org/bouncycastle2/crypto/digests/RIPEMD160Digest:RL	(II)I
    //   6076: iadd
    //   6077: wide
    //   6081: aload_0
    //   6082: wide
    //   6086: bipush 10
    //   6088: invokespecial 74	org/bouncycastle2/crypto/digests/RIPEMD160Digest:RL	(II)I
    //   6091: wide
    //   6095: wide
    //   6099: aload_0
    //   6100: ldc 90
    //   6102: wide
    //   6106: aload_0
    //   6107: wide
    //   6111: wide
    //   6115: wide
    //   6119: invokespecial 77	org/bouncycastle2/crypto/digests/RIPEMD160Digest:f5	(III)I
    //   6122: iadd
    //   6123: aload_0
    //   6124: getfield 21	org/bouncycastle2/crypto/digests/RIPEMD160Digest:X	[I
    //   6127: bipush 10
    //   6129: iaload
    //   6130: iadd
    //   6131: iadd
    //   6132: bipush 12
    //   6134: invokespecial 74	org/bouncycastle2/crypto/digests/RIPEMD160Digest:RL	(II)I
    //   6137: iadd
    //   6138: wide
    //   6142: aload_0
    //   6143: wide
    //   6147: bipush 10
    //   6149: invokespecial 74	org/bouncycastle2/crypto/digests/RIPEMD160Digest:RL	(II)I
    //   6152: wide
    //   6156: wide
    //   6160: aload_0
    //   6161: ldc 90
    //   6163: wide
    //   6167: aload_0
    //   6168: wide
    //   6172: wide
    //   6176: wide
    //   6180: invokespecial 77	org/bouncycastle2/crypto/digests/RIPEMD160Digest:f5	(III)I
    //   6183: iadd
    //   6184: aload_0
    //   6185: getfield 21	org/bouncycastle2/crypto/digests/RIPEMD160Digest:X	[I
    //   6188: bipush 14
    //   6190: iaload
    //   6191: iadd
    //   6192: iadd
    //   6193: iconst_5
    //   6194: invokespecial 74	org/bouncycastle2/crypto/digests/RIPEMD160Digest:RL	(II)I
    //   6197: iadd
    //   6198: wide
    //   6202: aload_0
    //   6203: wide
    //   6207: bipush 10
    //   6209: invokespecial 74	org/bouncycastle2/crypto/digests/RIPEMD160Digest:RL	(II)I
    //   6212: wide
    //   6216: wide
    //   6220: aload_0
    //   6221: ldc 90
    //   6223: wide
    //   6227: aload_0
    //   6228: wide
    //   6232: wide
    //   6236: wide
    //   6240: invokespecial 77	org/bouncycastle2/crypto/digests/RIPEMD160Digest:f5	(III)I
    //   6243: iadd
    //   6244: aload_0
    //   6245: getfield 21	org/bouncycastle2/crypto/digests/RIPEMD160Digest:X	[I
    //   6248: iconst_1
    //   6249: iaload
    //   6250: iadd
    //   6251: iadd
    //   6252: bipush 12
    //   6254: invokespecial 74	org/bouncycastle2/crypto/digests/RIPEMD160Digest:RL	(II)I
    //   6257: iadd
    //   6258: wide
    //   6262: aload_0
    //   6263: wide
    //   6267: bipush 10
    //   6269: invokespecial 74	org/bouncycastle2/crypto/digests/RIPEMD160Digest:RL	(II)I
    //   6272: wide
    //   6276: wide
    //   6280: aload_0
    //   6281: ldc 90
    //   6283: wide
    //   6287: aload_0
    //   6288: wide
    //   6292: wide
    //   6296: wide
    //   6300: invokespecial 77	org/bouncycastle2/crypto/digests/RIPEMD160Digest:f5	(III)I
    //   6303: iadd
    //   6304: aload_0
    //   6305: getfield 21	org/bouncycastle2/crypto/digests/RIPEMD160Digest:X	[I
    //   6308: iconst_3
    //   6309: iaload
    //   6310: iadd
    //   6311: iadd
    //   6312: bipush 13
    //   6314: invokespecial 74	org/bouncycastle2/crypto/digests/RIPEMD160Digest:RL	(II)I
    //   6317: iadd
    //   6318: wide
    //   6322: aload_0
    //   6323: wide
    //   6327: bipush 10
    //   6329: invokespecial 74	org/bouncycastle2/crypto/digests/RIPEMD160Digest:RL	(II)I
    //   6332: wide
    //   6336: wide
    //   6340: aload_0
    //   6341: ldc 90
    //   6343: wide
    //   6347: aload_0
    //   6348: wide
    //   6352: wide
    //   6356: wide
    //   6360: invokespecial 77	org/bouncycastle2/crypto/digests/RIPEMD160Digest:f5	(III)I
    //   6363: iadd
    //   6364: aload_0
    //   6365: getfield 21	org/bouncycastle2/crypto/digests/RIPEMD160Digest:X	[I
    //   6368: bipush 8
    //   6370: iaload
    //   6371: iadd
    //   6372: iadd
    //   6373: bipush 14
    //   6375: invokespecial 74	org/bouncycastle2/crypto/digests/RIPEMD160Digest:RL	(II)I
    //   6378: iadd
    //   6379: wide
    //   6383: aload_0
    //   6384: wide
    //   6388: bipush 10
    //   6390: invokespecial 74	org/bouncycastle2/crypto/digests/RIPEMD160Digest:RL	(II)I
    //   6393: wide
    //   6397: wide
    //   6401: aload_0
    //   6402: ldc 90
    //   6404: wide
    //   6408: aload_0
    //   6409: wide
    //   6413: wide
    //   6417: wide
    //   6421: invokespecial 77	org/bouncycastle2/crypto/digests/RIPEMD160Digest:f5	(III)I
    //   6424: iadd
    //   6425: aload_0
    //   6426: getfield 21	org/bouncycastle2/crypto/digests/RIPEMD160Digest:X	[I
    //   6429: bipush 11
    //   6431: iaload
    //   6432: iadd
    //   6433: iadd
    //   6434: bipush 11
    //   6436: invokespecial 74	org/bouncycastle2/crypto/digests/RIPEMD160Digest:RL	(II)I
    //   6439: iadd
    //   6440: wide
    //   6444: aload_0
    //   6445: wide
    //   6449: bipush 10
    //   6451: invokespecial 74	org/bouncycastle2/crypto/digests/RIPEMD160Digest:RL	(II)I
    //   6454: wide
    //   6458: wide
    //   6462: aload_0
    //   6463: ldc 90
    //   6465: wide
    //   6469: aload_0
    //   6470: wide
    //   6474: wide
    //   6478: wide
    //   6482: invokespecial 77	org/bouncycastle2/crypto/digests/RIPEMD160Digest:f5	(III)I
    //   6485: iadd
    //   6486: aload_0
    //   6487: getfield 21	org/bouncycastle2/crypto/digests/RIPEMD160Digest:X	[I
    //   6490: bipush 6
    //   6492: iaload
    //   6493: iadd
    //   6494: iadd
    //   6495: bipush 8
    //   6497: invokespecial 74	org/bouncycastle2/crypto/digests/RIPEMD160Digest:RL	(II)I
    //   6500: iadd
    //   6501: wide
    //   6505: aload_0
    //   6506: wide
    //   6510: bipush 10
    //   6512: invokespecial 74	org/bouncycastle2/crypto/digests/RIPEMD160Digest:RL	(II)I
    //   6515: wide
    //   6519: wide
    //   6523: aload_0
    //   6524: ldc 90
    //   6526: wide
    //   6530: aload_0
    //   6531: wide
    //   6535: wide
    //   6539: wide
    //   6543: invokespecial 77	org/bouncycastle2/crypto/digests/RIPEMD160Digest:f5	(III)I
    //   6546: iadd
    //   6547: aload_0
    //   6548: getfield 21	org/bouncycastle2/crypto/digests/RIPEMD160Digest:X	[I
    //   6551: bipush 15
    //   6553: iaload
    //   6554: iadd
    //   6555: iadd
    //   6556: iconst_5
    //   6557: invokespecial 74	org/bouncycastle2/crypto/digests/RIPEMD160Digest:RL	(II)I
    //   6560: iadd
    //   6561: wide
    //   6565: aload_0
    //   6566: wide
    //   6570: bipush 10
    //   6572: invokespecial 74	org/bouncycastle2/crypto/digests/RIPEMD160Digest:RL	(II)I
    //   6575: wide
    //   6579: wide
    //   6583: aload_0
    //   6584: ldc 90
    //   6586: wide
    //   6590: aload_0
    //   6591: wide
    //   6595: wide
    //   6599: wide
    //   6603: invokespecial 77	org/bouncycastle2/crypto/digests/RIPEMD160Digest:f5	(III)I
    //   6606: iadd
    //   6607: aload_0
    //   6608: getfield 21	org/bouncycastle2/crypto/digests/RIPEMD160Digest:X	[I
    //   6611: bipush 13
    //   6613: iaload
    //   6614: iadd
    //   6615: iadd
    //   6616: bipush 6
    //   6618: invokespecial 74	org/bouncycastle2/crypto/digests/RIPEMD160Digest:RL	(II)I
    //   6621: iadd
    //   6622: wide
    //   6626: aload_0
    //   6627: wide
    //   6631: bipush 10
    //   6633: invokespecial 74	org/bouncycastle2/crypto/digests/RIPEMD160Digest:RL	(II)I
    //   6636: wide
    //   6640: wide
    //   6644: aload_0
    //   6645: wide
    //   6649: aload_0
    //   6650: wide
    //   6654: wide
    //   6658: wide
    //   6662: invokespecial 72	org/bouncycastle2/crypto/digests/RIPEMD160Digest:f1	(III)I
    //   6665: iadd
    //   6666: aload_0
    //   6667: getfield 21	org/bouncycastle2/crypto/digests/RIPEMD160Digest:X	[I
    //   6670: bipush 12
    //   6672: iaload
    //   6673: iadd
    //   6674: bipush 8
    //   6676: invokespecial 74	org/bouncycastle2/crypto/digests/RIPEMD160Digest:RL	(II)I
    //   6679: iadd
    //   6680: wide
    //   6684: aload_0
    //   6685: wide
    //   6689: bipush 10
    //   6691: invokespecial 74	org/bouncycastle2/crypto/digests/RIPEMD160Digest:RL	(II)I
    //   6694: wide
    //   6698: wide
    //   6702: aload_0
    //   6703: wide
    //   6707: aload_0
    //   6708: wide
    //   6712: wide
    //   6716: wide
    //   6720: invokespecial 72	org/bouncycastle2/crypto/digests/RIPEMD160Digest:f1	(III)I
    //   6723: iadd
    //   6724: aload_0
    //   6725: getfield 21	org/bouncycastle2/crypto/digests/RIPEMD160Digest:X	[I
    //   6728: bipush 15
    //   6730: iaload
    //   6731: iadd
    //   6732: iconst_5
    //   6733: invokespecial 74	org/bouncycastle2/crypto/digests/RIPEMD160Digest:RL	(II)I
    //   6736: iadd
    //   6737: wide
    //   6741: aload_0
    //   6742: wide
    //   6746: bipush 10
    //   6748: invokespecial 74	org/bouncycastle2/crypto/digests/RIPEMD160Digest:RL	(II)I
    //   6751: wide
    //   6755: wide
    //   6759: aload_0
    //   6760: wide
    //   6764: aload_0
    //   6765: wide
    //   6769: wide
    //   6773: wide
    //   6777: invokespecial 72	org/bouncycastle2/crypto/digests/RIPEMD160Digest:f1	(III)I
    //   6780: iadd
    //   6781: aload_0
    //   6782: getfield 21	org/bouncycastle2/crypto/digests/RIPEMD160Digest:X	[I
    //   6785: bipush 10
    //   6787: iaload
    //   6788: iadd
    //   6789: bipush 12
    //   6791: invokespecial 74	org/bouncycastle2/crypto/digests/RIPEMD160Digest:RL	(II)I
    //   6794: iadd
    //   6795: wide
    //   6799: aload_0
    //   6800: wide
    //   6804: bipush 10
    //   6806: invokespecial 74	org/bouncycastle2/crypto/digests/RIPEMD160Digest:RL	(II)I
    //   6809: wide
    //   6813: wide
    //   6817: aload_0
    //   6818: wide
    //   6822: aload_0
    //   6823: wide
    //   6827: wide
    //   6831: wide
    //   6835: invokespecial 72	org/bouncycastle2/crypto/digests/RIPEMD160Digest:f1	(III)I
    //   6838: iadd
    //   6839: aload_0
    //   6840: getfield 21	org/bouncycastle2/crypto/digests/RIPEMD160Digest:X	[I
    //   6843: iconst_4
    //   6844: iaload
    //   6845: iadd
    //   6846: bipush 9
    //   6848: invokespecial 74	org/bouncycastle2/crypto/digests/RIPEMD160Digest:RL	(II)I
    //   6851: iadd
    //   6852: wide
    //   6856: aload_0
    //   6857: wide
    //   6861: bipush 10
    //   6863: invokespecial 74	org/bouncycastle2/crypto/digests/RIPEMD160Digest:RL	(II)I
    //   6866: wide
    //   6870: wide
    //   6874: aload_0
    //   6875: wide
    //   6879: aload_0
    //   6880: wide
    //   6884: wide
    //   6888: wide
    //   6892: invokespecial 72	org/bouncycastle2/crypto/digests/RIPEMD160Digest:f1	(III)I
    //   6895: iadd
    //   6896: aload_0
    //   6897: getfield 21	org/bouncycastle2/crypto/digests/RIPEMD160Digest:X	[I
    //   6900: iconst_1
    //   6901: iaload
    //   6902: iadd
    //   6903: bipush 12
    //   6905: invokespecial 74	org/bouncycastle2/crypto/digests/RIPEMD160Digest:RL	(II)I
    //   6908: iadd
    //   6909: wide
    //   6913: aload_0
    //   6914: wide
    //   6918: bipush 10
    //   6920: invokespecial 74	org/bouncycastle2/crypto/digests/RIPEMD160Digest:RL	(II)I
    //   6923: wide
    //   6927: wide
    //   6931: aload_0
    //   6932: wide
    //   6936: aload_0
    //   6937: wide
    //   6941: wide
    //   6945: wide
    //   6949: invokespecial 72	org/bouncycastle2/crypto/digests/RIPEMD160Digest:f1	(III)I
    //   6952: iadd
    //   6953: aload_0
    //   6954: getfield 21	org/bouncycastle2/crypto/digests/RIPEMD160Digest:X	[I
    //   6957: iconst_5
    //   6958: iaload
    //   6959: iadd
    //   6960: iconst_5
    //   6961: invokespecial 74	org/bouncycastle2/crypto/digests/RIPEMD160Digest:RL	(II)I
    //   6964: iadd
    //   6965: wide
    //   6969: aload_0
    //   6970: wide
    //   6974: bipush 10
    //   6976: invokespecial 74	org/bouncycastle2/crypto/digests/RIPEMD160Digest:RL	(II)I
    //   6979: wide
    //   6983: wide
    //   6987: aload_0
    //   6988: wide
    //   6992: aload_0
    //   6993: wide
    //   6997: wide
    //   7001: wide
    //   7005: invokespecial 72	org/bouncycastle2/crypto/digests/RIPEMD160Digest:f1	(III)I
    //   7008: iadd
    //   7009: aload_0
    //   7010: getfield 21	org/bouncycastle2/crypto/digests/RIPEMD160Digest:X	[I
    //   7013: bipush 8
    //   7015: iaload
    //   7016: iadd
    //   7017: bipush 14
    //   7019: invokespecial 74	org/bouncycastle2/crypto/digests/RIPEMD160Digest:RL	(II)I
    //   7022: iadd
    //   7023: wide
    //   7027: aload_0
    //   7028: wide
    //   7032: bipush 10
    //   7034: invokespecial 74	org/bouncycastle2/crypto/digests/RIPEMD160Digest:RL	(II)I
    //   7037: wide
    //   7041: wide
    //   7045: aload_0
    //   7046: wide
    //   7050: aload_0
    //   7051: wide
    //   7055: wide
    //   7059: wide
    //   7063: invokespecial 72	org/bouncycastle2/crypto/digests/RIPEMD160Digest:f1	(III)I
    //   7066: iadd
    //   7067: aload_0
    //   7068: getfield 21	org/bouncycastle2/crypto/digests/RIPEMD160Digest:X	[I
    //   7071: bipush 7
    //   7073: iaload
    //   7074: iadd
    //   7075: bipush 6
    //   7077: invokespecial 74	org/bouncycastle2/crypto/digests/RIPEMD160Digest:RL	(II)I
    //   7080: iadd
    //   7081: wide
    //   7085: aload_0
    //   7086: wide
    //   7090: bipush 10
    //   7092: invokespecial 74	org/bouncycastle2/crypto/digests/RIPEMD160Digest:RL	(II)I
    //   7095: wide
    //   7099: wide
    //   7103: aload_0
    //   7104: wide
    //   7108: aload_0
    //   7109: wide
    //   7113: wide
    //   7117: wide
    //   7121: invokespecial 72	org/bouncycastle2/crypto/digests/RIPEMD160Digest:f1	(III)I
    //   7124: iadd
    //   7125: aload_0
    //   7126: getfield 21	org/bouncycastle2/crypto/digests/RIPEMD160Digest:X	[I
    //   7129: bipush 6
    //   7131: iaload
    //   7132: iadd
    //   7133: bipush 8
    //   7135: invokespecial 74	org/bouncycastle2/crypto/digests/RIPEMD160Digest:RL	(II)I
    //   7138: iadd
    //   7139: wide
    //   7143: aload_0
    //   7144: wide
    //   7148: bipush 10
    //   7150: invokespecial 74	org/bouncycastle2/crypto/digests/RIPEMD160Digest:RL	(II)I
    //   7153: wide
    //   7157: wide
    //   7161: aload_0
    //   7162: wide
    //   7166: aload_0
    //   7167: wide
    //   7171: wide
    //   7175: wide
    //   7179: invokespecial 72	org/bouncycastle2/crypto/digests/RIPEMD160Digest:f1	(III)I
    //   7182: iadd
    //   7183: aload_0
    //   7184: getfield 21	org/bouncycastle2/crypto/digests/RIPEMD160Digest:X	[I
    //   7187: iconst_2
    //   7188: iaload
    //   7189: iadd
    //   7190: bipush 13
    //   7192: invokespecial 74	org/bouncycastle2/crypto/digests/RIPEMD160Digest:RL	(II)I
    //   7195: iadd
    //   7196: wide
    //   7200: aload_0
    //   7201: wide
    //   7205: bipush 10
    //   7207: invokespecial 74	org/bouncycastle2/crypto/digests/RIPEMD160Digest:RL	(II)I
    //   7210: wide
    //   7214: wide
    //   7218: aload_0
    //   7219: wide
    //   7223: aload_0
    //   7224: wide
    //   7228: wide
    //   7232: wide
    //   7236: invokespecial 72	org/bouncycastle2/crypto/digests/RIPEMD160Digest:f1	(III)I
    //   7239: iadd
    //   7240: aload_0
    //   7241: getfield 21	org/bouncycastle2/crypto/digests/RIPEMD160Digest:X	[I
    //   7244: bipush 13
    //   7246: iaload
    //   7247: iadd
    //   7248: bipush 6
    //   7250: invokespecial 74	org/bouncycastle2/crypto/digests/RIPEMD160Digest:RL	(II)I
    //   7253: iadd
    //   7254: wide
    //   7258: aload_0
    //   7259: wide
    //   7263: bipush 10
    //   7265: invokespecial 74	org/bouncycastle2/crypto/digests/RIPEMD160Digest:RL	(II)I
    //   7268: wide
    //   7272: wide
    //   7276: aload_0
    //   7277: wide
    //   7281: aload_0
    //   7282: wide
    //   7286: wide
    //   7290: wide
    //   7294: invokespecial 72	org/bouncycastle2/crypto/digests/RIPEMD160Digest:f1	(III)I
    //   7297: iadd
    //   7298: aload_0
    //   7299: getfield 21	org/bouncycastle2/crypto/digests/RIPEMD160Digest:X	[I
    //   7302: bipush 14
    //   7304: iaload
    //   7305: iadd
    //   7306: iconst_5
    //   7307: invokespecial 74	org/bouncycastle2/crypto/digests/RIPEMD160Digest:RL	(II)I
    //   7310: iadd
    //   7311: wide
    //   7315: aload_0
    //   7316: wide
    //   7320: bipush 10
    //   7322: invokespecial 74	org/bouncycastle2/crypto/digests/RIPEMD160Digest:RL	(II)I
    //   7325: wide
    //   7329: wide
    //   7333: aload_0
    //   7334: wide
    //   7338: aload_0
    //   7339: wide
    //   7343: wide
    //   7347: wide
    //   7351: invokespecial 72	org/bouncycastle2/crypto/digests/RIPEMD160Digest:f1	(III)I
    //   7354: iadd
    //   7355: aload_0
    //   7356: getfield 21	org/bouncycastle2/crypto/digests/RIPEMD160Digest:X	[I
    //   7359: iconst_0
    //   7360: iaload
    //   7361: iadd
    //   7362: bipush 15
    //   7364: invokespecial 74	org/bouncycastle2/crypto/digests/RIPEMD160Digest:RL	(II)I
    //   7367: iadd
    //   7368: wide
    //   7372: aload_0
    //   7373: wide
    //   7377: bipush 10
    //   7379: invokespecial 74	org/bouncycastle2/crypto/digests/RIPEMD160Digest:RL	(II)I
    //   7382: wide
    //   7386: wide
    //   7390: aload_0
    //   7391: wide
    //   7395: aload_0
    //   7396: wide
    //   7400: wide
    //   7404: wide
    //   7408: invokespecial 72	org/bouncycastle2/crypto/digests/RIPEMD160Digest:f1	(III)I
    //   7411: iadd
    //   7412: aload_0
    //   7413: getfield 21	org/bouncycastle2/crypto/digests/RIPEMD160Digest:X	[I
    //   7416: iconst_3
    //   7417: iaload
    //   7418: iadd
    //   7419: bipush 13
    //   7421: invokespecial 74	org/bouncycastle2/crypto/digests/RIPEMD160Digest:RL	(II)I
    //   7424: iadd
    //   7425: wide
    //   7429: aload_0
    //   7430: wide
    //   7434: bipush 10
    //   7436: invokespecial 74	org/bouncycastle2/crypto/digests/RIPEMD160Digest:RL	(II)I
    //   7439: wide
    //   7443: wide
    //   7447: aload_0
    //   7448: wide
    //   7452: aload_0
    //   7453: wide
    //   7457: wide
    //   7461: wide
    //   7465: invokespecial 72	org/bouncycastle2/crypto/digests/RIPEMD160Digest:f1	(III)I
    //   7468: iadd
    //   7469: aload_0
    //   7470: getfield 21	org/bouncycastle2/crypto/digests/RIPEMD160Digest:X	[I
    //   7473: bipush 9
    //   7475: iaload
    //   7476: iadd
    //   7477: bipush 11
    //   7479: invokespecial 74	org/bouncycastle2/crypto/digests/RIPEMD160Digest:RL	(II)I
    //   7482: iadd
    //   7483: wide
    //   7487: aload_0
    //   7488: wide
    //   7492: bipush 10
    //   7494: invokespecial 74	org/bouncycastle2/crypto/digests/RIPEMD160Digest:RL	(II)I
    //   7497: wide
    //   7501: wide
    //   7505: aload_0
    //   7506: wide
    //   7510: aload_0
    //   7511: wide
    //   7515: wide
    //   7519: wide
    //   7523: invokespecial 72	org/bouncycastle2/crypto/digests/RIPEMD160Digest:f1	(III)I
    //   7526: iadd
    //   7527: aload_0
    //   7528: getfield 21	org/bouncycastle2/crypto/digests/RIPEMD160Digest:X	[I
    //   7531: bipush 11
    //   7533: iaload
    //   7534: iadd
    //   7535: bipush 11
    //   7537: invokespecial 74	org/bouncycastle2/crypto/digests/RIPEMD160Digest:RL	(II)I
    //   7540: iadd
    //   7541: wide
    //   7545: aload_0
    //   7546: wide
    //   7550: bipush 10
    //   7552: invokespecial 74	org/bouncycastle2/crypto/digests/RIPEMD160Digest:RL	(II)I
    //   7555: wide
    //   7559: aload_0
    //   7560: getfield 32	org/bouncycastle2/crypto/digests/RIPEMD160Digest:H1	I
    //   7563: iadd
    //   7564: iadd
    //   7565: wide
    //   7569: aload_0
    //   7570: wide
    //   7574: wide
    //   7578: aload_0
    //   7579: getfield 34	org/bouncycastle2/crypto/digests/RIPEMD160Digest:H2	I
    //   7582: iadd
    //   7583: iadd
    //   7584: putfield 32	org/bouncycastle2/crypto/digests/RIPEMD160Digest:H1	I
    //   7587: aload_0
    //   7588: wide
    //   7592: wide
    //   7596: aload_0
    //   7597: getfield 36	org/bouncycastle2/crypto/digests/RIPEMD160Digest:H3	I
    //   7600: iadd
    //   7601: iadd
    //   7602: putfield 34	org/bouncycastle2/crypto/digests/RIPEMD160Digest:H2	I
    //   7605: aload_0
    //   7606: wide
    //   7610: wide
    //   7614: aload_0
    //   7615: getfield 38	org/bouncycastle2/crypto/digests/RIPEMD160Digest:H4	I
    //   7618: iadd
    //   7619: iadd
    //   7620: putfield 36	org/bouncycastle2/crypto/digests/RIPEMD160Digest:H3	I
    //   7623: aload_0
    //   7624: wide
    //   7628: wide
    //   7632: aload_0
    //   7633: getfield 30	org/bouncycastle2/crypto/digests/RIPEMD160Digest:H0	I
    //   7636: iadd
    //   7637: iadd
    //   7638: putfield 38	org/bouncycastle2/crypto/digests/RIPEMD160Digest:H4	I
    //   7641: aload_0
    //   7642: wide
    //   7646: putfield 30	org/bouncycastle2/crypto/digests/RIPEMD160Digest:H0	I
    //   7649: aload_0
    //   7650: iconst_0
    //   7651: putfield 46	org/bouncycastle2/crypto/digests/RIPEMD160Digest:xOff	I
    //   7654: iconst_0
    //   7655: wide
    //   7659: wide
    //   7663: aload_0
    //   7664: getfield 21	org/bouncycastle2/crypto/digests/RIPEMD160Digest:X	[I
    //   7667: arraylength
    //   7668: if_icmpne +4 -> 7672
    //   7671: return
    //   7672: aload_0
    //   7673: getfield 21	org/bouncycastle2/crypto/digests/RIPEMD160Digest:X	[I
    //   7676: wide
    //   7680: iconst_0
    //   7681: iastore
    //   7682: wide
    //   7688: goto -29 -> 7659
  }

  protected void processLength(long paramLong)
  {
    if (this.xOff > 14)
      processBlock();
    this.X[14] = ((int)(0xFFFFFFFF & paramLong));
    this.X[15] = ((int)(paramLong >>> 32));
  }

  protected void processWord(byte[] paramArrayOfByte, int paramInt)
  {
    int[] arrayOfInt = this.X;
    int i = this.xOff;
    this.xOff = (i + 1);
    arrayOfInt[i] = (0xFF & paramArrayOfByte[paramInt] | (0xFF & paramArrayOfByte[(paramInt + 1)]) << 8 | (0xFF & paramArrayOfByte[(paramInt + 2)]) << 16 | (0xFF & paramArrayOfByte[(paramInt + 3)]) << 24);
    if (this.xOff == 16)
      processBlock();
  }

  public void reset()
  {
    super.reset();
    this.H0 = 1732584193;
    this.H1 = -271733879;
    this.H2 = -1732584194;
    this.H3 = 271733878;
    this.H4 = -1009589776;
    this.xOff = 0;
    for (int i = 0; ; i++)
    {
      if (i == this.X.length)
        return;
      this.X[i] = 0;
    }
  }
}